[
  {
    "title": "Secure Easy Wins with Astrea's PvZ Blink All-in",
    "steps": [
      {
        "supply": "12",
        "time": "0:00",
        "action": "Probe",
        "interpretedAction": {
          "unitType": 84,
          "upgradeType": null,
          "count": 1,
          "isUpgrade": false,
          "isChronoBoosted": false,
          "specialAction": null
        },
        "comment": ""
      },
      {
        "supply": "13",
        "time": "0:12",
        "action": "Probe",
        "interpretedAction": {
          "unitType": 84,
          "upgradeType": null,
          "count": 1,
          "isUpgrade": false,
          "isChronoBoosted": false,
          "specialAction": null
        },
        "comment": ""
      },
      {
        "supply": "14",
        "time": "0:17",
        "action": "Pylon",
        "interpretedAction": {
          "unitType": 60,
          "upgradeType": null,
          "count": 1,
          "isUpgrade": false,
          "isChronoBoosted": false,
          "specialAction": null
        },
        "comment": ""
      },
      {
        "supply": "14",
        "time": "0:24",
        "action": "Probe (Chrono Boost)",
        "interpretedAction": {
          "unitType": 84,
          "upgradeType": null,
          "count": 1,
          "isUpgrade": false,
          "isChronoBoosted": true,
          "specialAction": null
        },
        "comment": ""
      },
      {
        "supply": "16",
        "time": "0:36",
        "action": "Probe (Chrono Boost)",
        "interpretedAction": {
          "unitType": 84,
          "upgradeType": null,
          "count": 1,
          "isUpgrade": false,
          "isChronoBoosted": true,
          "specialAction": null
        },
        "comment": ""
      },
      {
        "supply": "16",
        "time": "0:40",
        "action": "Gateway",
        "interpretedAction": {
          "unitType": 62,
          "upgradeType": null,
          "count": 1,
          "isUpgrade": false,
          "isChronoBoosted": false,
          "specialAction": null
        },
        "comment": ""
      },
      {
        "supply": "16",
        "time": "0:43",
        "action": "Probe (Chrono Boost)",
        "interpretedAction": {
          "unitType": 84,
          "upgradeType": null,
          "count": 1,
          "isUpgrade": false,
          "isChronoBoosted": true,
          "specialAction": null
        },
        "comment": ""
      },
      {
        "supply": "17",
        "time": "0:51",
        "action": "Probe",
        "interpretedAction": {
          "unitType": 84,
          "upgradeType": null,
          "count": 1,
          "isUpgrade": false,
          "isChronoBoosted": false,
          "specialAction": null
        },
        "comment": ""
      },
      {
        "supply": "17",
        "time": "0:52",
        "action": "Assimilator",
        "interpretedAction": {
          "unitType": 61,
          "upgradeType": null,
          "count": 1,
          "isUpgrade": false,
          "isChronoBoosted": false,
          "specialAction": null
        },
        "comment": ""
      },
      {
        "supply": "18",
        "time": "1:03",
        "action": "Probe",
        "interpretedAction": {
          "unitType": 84,
          "upgradeType": null,
          "count": 1,
          "isUpgrade": false,
          "isChronoBoosted": false,
          "specialAction": null
        },
        "comment": ""
      },
      {
        "supply": "19",
        "time": "1:15",
        "action": "Probe",
        "interpretedAction": {
          "unitType": 84,
          "upgradeType": null,
          "count": 1,
          "isUpgrade": false,
          "isChronoBoosted": false,
          "specialAction": null
        },
        "comment": ""
      },
      {
        "supply": "20",
        "time": "1:25",
        "action": "Nexus",
        "interpretedAction": {
          "unitType": 59,
          "upgradeType": null,
          "count": 1,
          "isUpgrade": false,
          "isChronoBoosted": false,
          "specialAction": null
        },
        "comment": ""
      },
      {
        "supply": "20",
        "time": "1:28",
        "action": "Probe",
        "interpretedAction": {
          "unitType": 84,
          "upgradeType": null,
          "count": 1,
          "isUpgrade": false,
          "isChronoBoosted": false,
          "specialAction": null
        },
        "comment": ""
      },
      {
        "supply": "21",
        "time": "1:38",
        "action": "Cybernetics Core",
        "interpretedAction": {
          "unitType": 72,
          "upgradeType": null,
          "count": 1,
          "isUpgrade": false,
          "isChronoBoosted": false,
          "specialAction": null
        },
        "comment": ""
      },
      {
        "supply": "21",
        "time": "1:45",
        "action": "Assimilator",
        "interpretedAction": {
          "unitType": 61,
          "upgradeType": null,
          "count": 1,
          "isUpgrade": false,
          "isChronoBoosted": false,
          "specialAction": null
        },
        "comment": ""
      },
      {
        "supply": "21",
        "time": "1:47",
        "action": "Probe",
        "interpretedAction": {
          "unitType": 84,
          "upgradeType": null,
          "count": 1,
          "isUpgrade": false,
          "isChronoBoosted": false,
          "specialAction": null
        },
        "comment": ""
      },
      {
        "supply": "21",
        "time": "1:53",
        "action": "Pylon",
        "interpretedAction": {
          "unitType": 60,
          "upgradeType": null,
          "count": 1,
          "isUpgrade": false,
          "isChronoBoosted": false,
          "specialAction": null
        },
        "comment": ""
      },
      {
        "supply": "23",
        "time": "2:12",
        "action": "Adept (Chrono Boost)",
        "interpretedAction": {
          "unitType": 311,
          "upgradeType": null,
          "count": 1,
          "isUpgrade": false,
          "isChronoBoosted": true,
          "specialAction": null
        },
        "comment": ""
      },
      {
        "supply": "23",
        "time": "2:15",
        "action": "Warp Gate",
        "interpretedAction": {
          "unitType": 133,
          "upgradeType": null,
          "count": 1,
          "isUpgrade": false,
          "isChronoBoosted": false,
          "specialAction": null
        },
        "comment": ""
      },
      {
        "supply": "27",
        "time": "2:23",
        "action": "Twilight Council",
        "interpretedAction": {
          "unitType": 65,
          "upgradeType": null,
          "count": 1,
          "isUpgrade": false,
          "isChronoBoosted": false,
          "specialAction": null
        },
        "comment": ""
      },
      {
        "supply": "28",
        "time": "2:33",
        "action": "Stalker (Chrono Boost)",
        "interpretedAction": {
          "unitType": 74,
          "upgradeType": null,
          "count": 1,
          "isUpgrade": false,
          "isChronoBoosted": true,
          "specialAction": null
        },
        "comment": ""
      },
      {
        "supply": "33",
        "time": "2:55",
        "action": "Robotics Facility",
        "interpretedAction": {
          "unitType": 71,
          "upgradeType": null,
          "count": 1,
          "isUpgrade": false,
          "isChronoBoosted": false,
          "specialAction": null
        },
        "comment": ""
      },
      {
        "supply": "36",
        "time": "3:13",
        "action": "Blink (Chrono Boost)",
        "interpretedAction": {
          "unitType": null,
          "upgradeType": 87,
          "count": 1,
          "isUpgrade": true,
          "isChronoBoosted": true,
          "specialAction": null
        },
        "comment": ""
      },
      {
        "supply": "36",
        "time": "3:15",
        "action": "Gateway",
        "interpretedAction": {
          "unitType": 62,
          "upgradeType": null,
          "count": 1,
          "isUpgrade": false,
          "isChronoBoosted": false,
          "specialAction": null
        },
        "comment": ""
      },
      {
        "supply": "38",
        "time": "3:25",
        "action": "Adept",
        "interpretedAction": {
          "unitType": 311,
          "upgradeType": null,
          "count": 1,
          "isUpgrade": false,
          "isChronoBoosted": false,
          "specialAction": null
        },
        "comment": ""
      },
      {
        "supply": "42",
        "time": "3:37",
        "action": "Pylon",
        "interpretedAction": {
          "unitType": 60,
          "upgradeType": null,
          "count": 1,
          "isUpgrade": false,
          "isChronoBoosted": false,
          "specialAction": null
        },
        "comment": ""
      },
      {
        "supply": "42",
        "time": "3:41",
        "action": "Warp Prism (Chrono Boost)",
        "interpretedAction": {
          "unitType": 81,
          "upgradeType": null,
          "count": 1,
          "isUpgrade": false,
          "isChronoBoosted": true,
          "specialAction": null
        },
        "comment": ""
      },
      {
        "supply": "46",
        "time": "3:52",
        "action": "Pylon",
        "interpretedAction": {
          "unitType": 60,
          "upgradeType": null,
          "count": 1,
          "isUpgrade": false,
          "isChronoBoosted": false,
          "specialAction": null
        },
        "comment": ""
      },
      {
        "supply": "48",
        "time": "4:04",
        "action": "Adept",
        "interpretedAction": {
          "unitType": 311,
          "upgradeType": null,
          "count": 1,
          "isUpgrade": false,
          "isChronoBoosted": false,
          "specialAction": null
        },
        "comment": ""
      },
      {
        "supply": "48",
        "time": "4:07",
        "action": "Assimilator",
        "interpretedAction": {
          "unitType": 61,
          "upgradeType": null,
          "count": 1,
          "isUpgrade": false,
          "isChronoBoosted": false,
          "specialAction": null
        },
        "comment": ""
      },
      {
        "supply": "48",
        "time": "4:09",
        "action": "Adept",
        "interpretedAction": {
          "unitType": 311,
          "upgradeType": null,
          "count": 1,
          "isUpgrade": false,
          "isChronoBoosted": false,
          "specialAction": null
        },
        "comment": ""
      },
      {
        "supply": "53",
        "time": "4:14",
        "action": "Observer",
        "interpretedAction": {
          "unitType": 82,
          "upgradeType": null,
          "count": 1,
          "isUpgrade": false,
          "isChronoBoosted": false,
          "specialAction": null
        },
        "comment": ""
      },
      {
        "supply": "54",
        "time": "4:22",
        "action": "Gateway x3",
        "interpretedAction": {
          "unitType": 62,
          "upgradeType": null,
          "count": 3,
          "isUpgrade": false,
          "isChronoBoosted": false,
          "specialAction": null
        },
        "comment": ""
      },
      {
        "supply": "54",
        "time": "4:27",
        "action": "Gateway",
        "interpretedAction": {
          "unitType": 62,
          "upgradeType": null,
          "count": 1,
          "isUpgrade": false,
          "isChronoBoosted": false,
          "specialAction": null
        },
        "comment": ""
      },
      {
        "supply": "54",
        "time": "4:37",
        "action": "Gateway",
        "interpretedAction": {
          "unitType": 62,
          "upgradeType": null,
          "count": 1,
          "isUpgrade": false,
          "isChronoBoosted": false,
          "specialAction": null
        },
        "comment": ""
      },
      {
        "supply": "54",
        "time": "4:44",
        "action": "Stalker x2",
        "interpretedAction": {
          "unitType": 74,
          "upgradeType": null,
          "count": 2,
          "isUpgrade": false,
          "isChronoBoosted": false,
          "specialAction": null
        },
        "comment": ""
      },
      {
        "supply": "58",
        "time": "4:51",
        "action": "Pylon",
        "interpretedAction": {
          "unitType": 60,
          "upgradeType": null,
          "count": 1,
          "isUpgrade": false,
          "isChronoBoosted": false,
          "specialAction": null
        },
        "comment": ""
      },
      {
        "supply": "58",
        "time": "5:10",
        "action": "Stalker x2",
        "interpretedAction": {
          "unitType": 74,
          "upgradeType": null,
          "count": 2,
          "isUpgrade": false,
          "isChronoBoosted": false,
          "specialAction": null
        },
        "comment": ""
      },
      {
        "supply": "62",
        "time": "5:18",
        "action": "Stalker x2",
        "interpretedAction": {
          "unitType": 74,
          "upgradeType": null,
          "count": 2,
          "isUpgrade": false,
          "isChronoBoosted": false,
          "specialAction": null
        },
        "comment": ""
      },
      {
        "supply": "66",
        "time": "5:29",
        "action": "Stalker x2",
        "interpretedAction": {
          "unitType": 74,
          "upgradeType": null,
          "count": 2,
          "isUpgrade": false,
          "isChronoBoosted": false,
          "specialAction": null
        },
        "comment": ""
      },
      {
        "supply": "66",
        "time": "5:31",
        "action": "Observer",
        "interpretedAction": {
          "unitType": 82,
          "upgradeType": null,
          "count": 1,
          "isUpgrade": false,
          "isChronoBoosted": false,
          "specialAction": null
        },
        "comment": ""
      },
      {
        "supply": "70",
        "time": "5:36",
        "action": "Stalker",
        "interpretedAction": {
          "unitType": 74,
          "upgradeType": null,
          "count": 1,
          "isUpgrade": false,
          "isChronoBoosted": false,
          "specialAction": null
        },
        "comment": ""
      },
      {
        "supply": "80",
        "time": "5:54",
        "action": "Observer",
        "interpretedAction": {
          "unitType": 82,
          "upgradeType": null,
          "count": 1,
          "isUpgrade": false,
          "isChronoBoosted": false,
          "specialAction": null
        },
        "comment": ""
      },
      {
        "supply": "90",
        "time": "6:17",
        "action": "Adept",
        "interpretedAction": {
          "unitType": 311,
          "upgradeType": null,
          "count": 1,
          "isUpgrade": false,
          "isChronoBoosted": false,
          "specialAction": null
        },
        "comment": ""
      },
      {
        "supply": "90",
        "time": "6:39",
        "action": "Zealot",
        "interpretedAction": {
          "unitType": 73,
          "upgradeType": null,
          "count": 1,
          "isUpgrade": false,
          "isChronoBoosted": false,
          "specialAction": null
        },
        "comment": ""
      },
      {
        "supply": "94",
        "time": "6:49",
        "action": "Adept",
        "interpretedAction": {
          "unitType": 311,
          "upgradeType": null,
          "count": 1,
          "isUpgrade": false,
          "isChronoBoosted": false,
          "specialAction": null
        },
        "comment": ""
      },
      {
        "supply": "108",
        "time": "7:17",
        "action": "Observer",
        "interpretedAction": {
          "unitType": 82,
          "upgradeType": null,
          "count": 1,
          "isUpgrade": false,
          "isChronoBoosted": false,
          "specialAction": null
        },
        "comment": ""
      },
      {
        "supply": "106",
        "time": "7:32",
        "action": "Gateway",
        "interpretedAction": {
          "unitType": 62,
          "upgradeType": null,
          "count": 1,
          "isUpgrade": false,
          "isChronoBoosted": false,
          "specialAction": null
        },
        "comment": ""
      },
      {
        "supply": "106",
        "time": "7:35",
        "action": "Zealot",
        "interpretedAction": {
          "unitType": 73,
          "upgradeType": null,
          "count": 1,
          "isUpgrade": false,
          "isChronoBoosted": false,
          "specialAction": null
        },
        "comment": ""
      },
      {
        "supply": "106",
        "time": "7:36",
        "action": "Adept",
        "interpretedAction": {
          "unitType": 311,
          "upgradeType": null,
          "count": 1,
          "isUpgrade": false,
          "isChronoBoosted": false,
          "specialAction": null
        },
        "comment": ""
      },
      {
        "supply": "110",
        "time": "7:43",
        "action": "Observer",
        "interpretedAction": {
          "unitType": 82,
          "upgradeType": null,
          "count": 1,
          "isUpgrade": false,
          "isChronoBoosted": false,
          "specialAction": null
        },
        "comment": ""
      },
      {
        "supply": "112",
        "time": "8:06",
        "action": "Observer",
        "interpretedAction": {
          "unitType": 82,
          "upgradeType": null,
          "count": 1,
          "isUpgrade": false,
          "isChronoBoosted": false,
          "specialAction": null
        },
        "comment": ""
      },
      {
        "supply": "112",
        "time": "8:07",
        "action": "Zealot x3",
        "interpretedAction": {
          "unitType": 73,
          "upgradeType": null,
          "count": 3,
          "isUpgrade": false,
          "isChronoBoosted": false,
          "specialAction": null
        },
        "comment": ""
      },
      {
        "supply": "128",
        "time": "9:00",
        "action": "Observer",
        "interpretedAction": {
          "unitType": 82,
          "upgradeType": null,
          "count": 1,
          "isUpgrade": false,
          "isChronoBoosted": false,
          "specialAction": null
        },
        "comment": ""
      },
      {
        "supply": "128",
        "time": "9:22",
        "action": "Zealot",
        "interpretedAction": {
          "unitType": 73,
          "upgradeType": null,
          "count": 1,
          "isUpgrade": false,
          "isChronoBoosted": false,
          "specialAction": null
        },
        "comment": ""
      }
    ],
    "raceMatchup": "PvZ",
    "url": "https://lotv.spawningtool.com/build/174808/"
  },
  {
    "title": "Standard Terran vs Terran (3 Reaper 2 Hellion)",
    "steps": [
      {
        "supply": "12",
        "time": "0:00",
        "action": "SCV",
        "interpretedAction": {
          "unitType": 45,
          "upgradeType": null,
          "count": 1,
          "isUpgrade": false,
          "isChronoBoosted": false,
          "specialAction": null
        },
        "comment": ""
      },
      {
        "supply": "13",
        "time": "0:12",
        "action": "SCV",
        "interpretedAction": {
          "unitType": 45,
          "upgradeType": null,
          "count": 1,
          "isUpgrade": false,
          "isChronoBoosted": false,
          "specialAction": null
        },
        "comment": ""
      },
      {
        "supply": "14",
        "time": "0:18",
        "action": "Supply Depot",
        "interpretedAction": {
          "unitType": 19,
          "upgradeType": null,
          "count": 1,
          "isUpgrade": false,
          "isChronoBoosted": false,
          "specialAction": null
        },
        "comment": ""
      },
      {
        "supply": "14",
        "time": "0:24",
        "action": "SCV",
        "interpretedAction": {
          "unitType": 45,
          "upgradeType": null,
          "count": 1,
          "isUpgrade": false,
          "isChronoBoosted": false,
          "specialAction": null
        },
        "comment": ""
      },
      {
        "supply": "15",
        "time": "0:40",
        "action": "SCV",
        "interpretedAction": {
          "unitType": 45,
          "upgradeType": null,
          "count": 1,
          "isUpgrade": false,
          "isChronoBoosted": false,
          "specialAction": null
        },
        "comment": ""
      },
      {
        "supply": "15",
        "time": "0:41",
        "action": "Barracks",
        "interpretedAction": {
          "unitType": 21,
          "upgradeType": null,
          "count": 1,
          "isUpgrade": false,
          "isChronoBoosted": false,
          "specialAction": null
        },
        "comment": ""
      },
      {
        "supply": "16",
        "time": "0:45",
        "action": "Refinery",
        "interpretedAction": {
          "unitType": 20,
          "upgradeType": null,
          "count": 1,
          "isUpgrade": false,
          "isChronoBoosted": false,
          "specialAction": null
        },
        "comment": ""
      },
      {
        "supply": "16",
        "time": "0:52",
        "action": "SCV",
        "interpretedAction": {
          "unitType": 45,
          "upgradeType": null,
          "count": 1,
          "isUpgrade": false,
          "isChronoBoosted": false,
          "specialAction": null
        },
        "comment": ""
      },
      {
        "supply": "16",
        "time": "0:54",
        "action": "Refinery",
        "interpretedAction": {
          "unitType": 20,
          "upgradeType": null,
          "count": 1,
          "isUpgrade": false,
          "isChronoBoosted": false,
          "specialAction": null
        },
        "comment": ""
      },
      {
        "supply": "17",
        "time": "1:04",
        "action": "SCV",
        "interpretedAction": {
          "unitType": 45,
          "upgradeType": null,
          "count": 1,
          "isUpgrade": false,
          "isChronoBoosted": false,
          "specialAction": null
        },
        "comment": ""
      },
      {
        "supply": "18",
        "time": "1:16",
        "action": "SCV",
        "interpretedAction": {
          "unitType": 45,
          "upgradeType": null,
          "count": 1,
          "isUpgrade": false,
          "isChronoBoosted": false,
          "specialAction": null
        },
        "comment": ""
      },
      {
        "supply": "19",
        "time": "1:28",
        "action": "Reaper, Orbital Command",
        "interpretedAction": {
          "unitType": 49,
          "upgradeType": null,
          "count": 1,
          "isUpgrade": false,
          "isChronoBoosted": false,
          "specialAction": null
        },
        "comment": ""
      },
      {
        "supply": "19",
        "time": "1:28",
        "action": "Reaper, Orbital Command",
        "interpretedAction": {
          "unitType": 132,
          "upgradeType": null,
          "count": 1,
          "isUpgrade": false,
          "isChronoBoosted": false,
          "specialAction": null
        },
        "comment": ""
      },
      {
        "supply": "19",
        "time": "1:31",
        "action": "Supply Depot",
        "interpretedAction": {
          "unitType": 19,
          "upgradeType": null,
          "count": 1,
          "isUpgrade": false,
          "isChronoBoosted": false,
          "specialAction": null
        },
        "comment": ""
      },
      {
        "supply": "20",
        "time": "1:42",
        "action": "Factory",
        "interpretedAction": {
          "unitType": 27,
          "upgradeType": null,
          "count": 1,
          "isUpgrade": false,
          "isChronoBoosted": false,
          "specialAction": null
        },
        "comment": ""
      },
      {
        "supply": "20",
        "time": "1:54",
        "action": "SCV",
        "interpretedAction": {
          "unitType": 45,
          "upgradeType": null,
          "count": 1,
          "isUpgrade": false,
          "isChronoBoosted": false,
          "specialAction": null
        },
        "comment": ""
      },
      {
        "supply": "21",
        "time": "2:03",
        "action": "Reaper",
        "interpretedAction": {
          "unitType": 49,
          "upgradeType": null,
          "count": 1,
          "isUpgrade": false,
          "isChronoBoosted": false,
          "specialAction": null
        },
        "comment": ""
      },
      {
        "supply": "21",
        "time": "2:06",
        "action": "SCV",
        "interpretedAction": {
          "unitType": 45,
          "upgradeType": null,
          "count": 1,
          "isUpgrade": false,
          "isChronoBoosted": false,
          "specialAction": null
        },
        "comment": ""
      },
      {
        "supply": "23",
        "time": "2:18",
        "action": "SCV",
        "interpretedAction": {
          "unitType": 45,
          "upgradeType": null,
          "count": 1,
          "isUpgrade": false,
          "isChronoBoosted": false,
          "specialAction": null
        },
        "comment": ""
      },
      {
        "supply": "23",
        "time": "2:21",
        "action": "Command Center",
        "interpretedAction": {
          "unitType": 18,
          "upgradeType": null,
          "count": 1,
          "isUpgrade": false,
          "isChronoBoosted": false,
          "specialAction": null
        },
        "comment": ""
      },
      {
        "supply": "24",
        "time": "2:28",
        "action": "Hellion",
        "interpretedAction": {
          "unitType": 53,
          "upgradeType": null,
          "count": 1,
          "isUpgrade": false,
          "isChronoBoosted": false,
          "specialAction": null
        },
        "comment": ""
      },
      {
        "supply": "26",
        "time": "2:32",
        "action": "Supply Depot",
        "interpretedAction": {
          "unitType": 19,
          "upgradeType": null,
          "count": 1,
          "isUpgrade": false,
          "isChronoBoosted": false,
          "specialAction": null
        },
        "comment": ""
      },
      {
        "supply": "26",
        "time": "2:35",
        "action": "Reaper",
        "interpretedAction": {
          "unitType": 49,
          "upgradeType": null,
          "count": 1,
          "isUpgrade": false,
          "isChronoBoosted": false,
          "specialAction": null
        },
        "comment": ""
      },
      {
        "supply": "28",
        "time": "2:47",
        "action": "Starport",
        "interpretedAction": {
          "unitType": 28,
          "upgradeType": null,
          "count": 1,
          "isUpgrade": false,
          "isChronoBoosted": false,
          "specialAction": null
        },
        "comment": ""
      },
      {
        "supply": "29",
        "time": "2:53",
        "action": "Hellion",
        "interpretedAction": {
          "unitType": 53,
          "upgradeType": null,
          "count": 1,
          "isUpgrade": false,
          "isChronoBoosted": false,
          "specialAction": null
        },
        "comment": ""
      },
      {
        "supply": "32",
        "time": "3:07",
        "action": "Barracks Reactor, Refinery",
        "interpretedAction": {
          "unitType": 38,
          "upgradeType": null,
          "count": 1,
          "isUpgrade": false,
          "isChronoBoosted": false,
          "specialAction": null
        },
        "comment": ""
      },
      {
        "supply": "32",
        "time": "3:07",
        "action": "Barracks Reactor, Refinery",
        "interpretedAction": {
          "unitType": 20,
          "upgradeType": null,
          "count": 1,
          "isUpgrade": false,
          "isChronoBoosted": false,
          "specialAction": null
        },
        "comment": ""
      },
      {
        "supply": "33",
        "time": "3:14",
        "action": "Factory Tech Lab",
        "interpretedAction": {
          "unitType": 39,
          "upgradeType": null,
          "count": 1,
          "isUpgrade": false,
          "isChronoBoosted": false,
          "specialAction": null
        },
        "comment": ""
      },
      {
        "supply": "33",
        "time": "3:24",
        "action": "Starport Tech Lab",
        "interpretedAction": {
          "unitType": 41,
          "upgradeType": null,
          "count": 1,
          "isUpgrade": false,
          "isChronoBoosted": false,
          "specialAction": null
        },
        "comment": ""
      },
      {
        "supply": "34",
        "time": "3:33",
        "action": "Orbital Command",
        "interpretedAction": {
          "unitType": 132,
          "upgradeType": null,
          "count": 1,
          "isUpgrade": false,
          "isChronoBoosted": false,
          "specialAction": null
        },
        "comment": ""
      },
      {
        "supply": "34",
        "time": "3:35",
        "action": "Cyclone",
        "interpretedAction": {
          "unitType": 692,
          "upgradeType": null,
          "count": 1,
          "isUpgrade": false,
          "isChronoBoosted": false,
          "specialAction": null
        },
        "comment": ""
      },
      {
        "supply": "38",
        "time": "3:43",
        "action": "Marine x2",
        "interpretedAction": {
          "unitType": 48,
          "upgradeType": null,
          "count": 2,
          "isUpgrade": false,
          "isChronoBoosted": false,
          "specialAction": null
        },
        "comment": ""
      },
      {
        "supply": "40",
        "time": "3:49",
        "action": "Raven",
        "interpretedAction": {
          "unitType": 56,
          "upgradeType": null,
          "count": 1,
          "isUpgrade": false,
          "isChronoBoosted": false,
          "specialAction": null
        },
        "comment": ""
      },
      {
        "supply": "43",
        "time": "3:56",
        "action": "Supply Depot",
        "interpretedAction": {
          "unitType": 19,
          "upgradeType": null,
          "count": 1,
          "isUpgrade": false,
          "isChronoBoosted": false,
          "specialAction": null
        },
        "comment": ""
      },
      {
        "supply": "43",
        "time": "4:01",
        "action": "Marine x2",
        "interpretedAction": {
          "unitType": 48,
          "upgradeType": null,
          "count": 2,
          "isUpgrade": false,
          "isChronoBoosted": false,
          "specialAction": null
        },
        "comment": ""
      },
      {
        "supply": "46",
        "time": "4:08",
        "action": "Siege Tank",
        "interpretedAction": {
          "unitType": 33,
          "upgradeType": null,
          "count": 1,
          "isUpgrade": false,
          "isChronoBoosted": false,
          "specialAction": null
        },
        "comment": ""
      },
      {
        "supply": "52",
        "time": "4:19",
        "action": "Supply Depot, Marine x2",
        "interpretedAction": {
          "unitType": 19,
          "upgradeType": null,
          "count": 2,
          "isUpgrade": false,
          "isChronoBoosted": false,
          "specialAction": null
        },
        "comment": ""
      },
      {
        "supply": "52",
        "time": "4:19",
        "action": "Supply Depot, Marine x2",
        "interpretedAction": {
          "unitType": 48,
          "upgradeType": null,
          "count": 2,
          "isUpgrade": false,
          "isChronoBoosted": false,
          "specialAction": null
        },
        "comment": ""
      },
      {
        "supply": "56",
        "time": "4:32",
        "action": "Raven",
        "interpretedAction": {
          "unitType": 56,
          "upgradeType": null,
          "count": 1,
          "isUpgrade": false,
          "isChronoBoosted": false,
          "specialAction": null
        },
        "comment": ""
      },
      {
        "supply": "59",
        "time": "4:39",
        "action": "Marine x2",
        "interpretedAction": {
          "unitType": 48,
          "upgradeType": null,
          "count": 2,
          "isUpgrade": false,
          "isChronoBoosted": false,
          "specialAction": null
        },
        "comment": ""
      },
      {
        "supply": "59",
        "time": "4:45",
        "action": "Siege Tank",
        "interpretedAction": {
          "unitType": 33,
          "upgradeType": null,
          "count": 1,
          "isUpgrade": false,
          "isChronoBoosted": false,
          "specialAction": null
        },
        "comment": ""
      },
      {
        "supply": "67",
        "time": "4:57",
        "action": "Marine x2",
        "interpretedAction": {
          "unitType": 48,
          "upgradeType": null,
          "count": 2,
          "isUpgrade": false,
          "isChronoBoosted": false,
          "specialAction": null
        },
        "comment": ""
      }
    ],
    "raceMatchup": "TvT",
    "url": "https://lotv.spawningtool.com/build/171779/"
  },
  {
    "title": "HuShang's Oracle 3 Gate Attack",
    "steps": [
      {
        "supply": "12",
        "time": "0:00",
        "action": "Probe",
        "interpretedAction": {
          "unitType": 84,
          "upgradeType": null,
          "count": 1,
          "isUpgrade": false,
          "isChronoBoosted": false,
          "specialAction": null
        },
        "comment": ""
      },
      {
        "supply": "13",
        "time": "0:12",
        "action": "Probe",
        "interpretedAction": {
          "unitType": 84,
          "upgradeType": null,
          "count": 1,
          "isUpgrade": false,
          "isChronoBoosted": false,
          "specialAction": null
        },
        "comment": ""
      },
      {
        "supply": "14",
        "time": "0:19",
        "action": "Pylon",
        "interpretedAction": {
          "unitType": 60,
          "upgradeType": null,
          "count": 1,
          "isUpgrade": false,
          "isChronoBoosted": false,
          "specialAction": null
        },
        "comment": ""
      },
      {
        "supply": "14",
        "time": "0:24",
        "action": "Probe",
        "interpretedAction": {
          "unitType": 84,
          "upgradeType": null,
          "count": 1,
          "isUpgrade": false,
          "isChronoBoosted": false,
          "specialAction": null
        },
        "comment": ""
      },
      {
        "supply": "15",
        "time": "0:37",
        "action": "Gateway, Probe (Chrono Boost)",
        "interpretedAction": {
          "unitType": 62,
          "upgradeType": null,
          "count": 1,
          "isUpgrade": false,
          "isChronoBoosted": true,
          "specialAction": null
        },
        "comment": ""
      },
      {
        "supply": "15",
        "time": "0:37",
        "action": "Gateway, Probe (Chrono Boost)",
        "interpretedAction": {
          "unitType": 84,
          "upgradeType": null,
          "count": 1,
          "isUpgrade": false,
          "isChronoBoosted": true,
          "specialAction": null
        },
        "comment": ""
      },
      {
        "supply": "16",
        "time": "0:43",
        "action": "Assimilator",
        "interpretedAction": {
          "unitType": 61,
          "upgradeType": null,
          "count": 1,
          "isUpgrade": false,
          "isChronoBoosted": false,
          "specialAction": null
        },
        "comment": ""
      },
      {
        "supply": "16",
        "time": "0:49",
        "action": "Probe (Chrono Boost)",
        "interpretedAction": {
          "unitType": 84,
          "upgradeType": null,
          "count": 1,
          "isUpgrade": false,
          "isChronoBoosted": true,
          "specialAction": null
        },
        "comment": ""
      },
      {
        "supply": "17",
        "time": "0:55",
        "action": "Probe (Chrono Boost)",
        "interpretedAction": {
          "unitType": 84,
          "upgradeType": null,
          "count": 1,
          "isUpgrade": false,
          "isChronoBoosted": true,
          "specialAction": null
        },
        "comment": ""
      },
      {
        "supply": "18",
        "time": "1:03",
        "action": "Probe (Chrono Boost)",
        "interpretedAction": {
          "unitType": 84,
          "upgradeType": null,
          "count": 1,
          "isUpgrade": false,
          "isChronoBoosted": true,
          "specialAction": null
        },
        "comment": ""
      },
      {
        "supply": "19",
        "time": "1:14",
        "action": "Probe x2 (Chrono Boost)",
        "interpretedAction": {
          "unitType": 84,
          "upgradeType": null,
          "count": 2,
          "isUpgrade": false,
          "isChronoBoosted": true,
          "specialAction": null
        },
        "comment": ""
      },
      {
        "supply": "20",
        "time": "1:25",
        "action": "Cybernetics Core",
        "interpretedAction": {
          "unitType": 72,
          "upgradeType": null,
          "count": 1,
          "isUpgrade": false,
          "isChronoBoosted": false,
          "specialAction": null
        },
        "comment": ""
      },
      {
        "supply": "21",
        "time": "1:38",
        "action": "Nexus",
        "interpretedAction": {
          "unitType": 59,
          "upgradeType": null,
          "count": 1,
          "isUpgrade": false,
          "isChronoBoosted": false,
          "specialAction": null
        },
        "comment": ""
      },
      {
        "supply": "21",
        "time": "1:45",
        "action": "Pylon",
        "interpretedAction": {
          "unitType": 60,
          "upgradeType": null,
          "count": 1,
          "isUpgrade": false,
          "isChronoBoosted": false,
          "specialAction": null
        },
        "comment": ""
      },
      {
        "supply": "21",
        "time": "1:50",
        "action": "Assimilator",
        "interpretedAction": {
          "unitType": 61,
          "upgradeType": null,
          "count": 1,
          "isUpgrade": false,
          "isChronoBoosted": false,
          "specialAction": null
        },
        "comment": ""
      },
      {
        "supply": "21",
        "time": "1:53",
        "action": "Probe",
        "interpretedAction": {
          "unitType": 84,
          "upgradeType": null,
          "count": 1,
          "isUpgrade": false,
          "isChronoBoosted": false,
          "specialAction": null
        },
        "comment": ""
      },
      {
        "supply": "22",
        "time": "2:02",
        "action": "Adept (Chrono Boost)",
        "interpretedAction": {
          "unitType": 311,
          "upgradeType": null,
          "count": 1,
          "isUpgrade": false,
          "isChronoBoosted": true,
          "specialAction": null
        },
        "comment": ""
      },
      {
        "supply": "25",
        "time": "2:18",
        "action": "Stargate",
        "interpretedAction": {
          "unitType": 67,
          "upgradeType": null,
          "count": 1,
          "isUpgrade": false,
          "isChronoBoosted": false,
          "specialAction": null
        },
        "comment": ""
      },
      {
        "supply": "26",
        "time": "2:23",
        "action": "Adept",
        "interpretedAction": {
          "unitType": 311,
          "upgradeType": null,
          "count": 1,
          "isUpgrade": false,
          "isChronoBoosted": false,
          "specialAction": null
        },
        "comment": ""
      },
      {
        "supply": "29",
        "time": "2:30",
        "action": "Warp Gate (Chrono Boost)",
        "interpretedAction": {
          "unitType": 133,
          "upgradeType": null,
          "count": 1,
          "isUpgrade": false,
          "isChronoBoosted": true,
          "specialAction": null
        },
        "comment": ""
      },
      {
        "supply": "32",
        "time": "2:59",
        "action": "Oracle (Chrono Boost)",
        "interpretedAction": {
          "unitType": 495,
          "upgradeType": null,
          "count": 1,
          "isUpgrade": false,
          "isChronoBoosted": true,
          "specialAction": null
        },
        "comment": ""
      },
      {
        "supply": "32",
        "time": "3:05",
        "action": "Gateway",
        "interpretedAction": {
          "unitType": 62,
          "upgradeType": null,
          "count": 1,
          "isUpgrade": false,
          "isChronoBoosted": false,
          "specialAction": null
        },
        "comment": ""
      },
      {
        "supply": "36",
        "time": "3:11",
        "action": "Gateway",
        "interpretedAction": {
          "unitType": 62,
          "upgradeType": null,
          "count": 1,
          "isUpgrade": false,
          "isChronoBoosted": false,
          "specialAction": null
        },
        "comment": ""
      },
      {
        "supply": "39",
        "time": "3:29",
        "action": "Oracle (Chrono Boost)",
        "interpretedAction": {
          "unitType": 495,
          "upgradeType": null,
          "count": 1,
          "isUpgrade": false,
          "isChronoBoosted": true,
          "specialAction": null
        },
        "comment": ""
      },
      {
        "supply": "44",
        "time": "3:40",
        "action": "Pylon",
        "interpretedAction": {
          "unitType": 60,
          "upgradeType": null,
          "count": 1,
          "isUpgrade": false,
          "isChronoBoosted": false,
          "specialAction": null
        },
        "comment": ""
      },
      {
        "supply": "44",
        "time": "3:48",
        "action": "Pylon",
        "interpretedAction": {
          "unitType": 60,
          "upgradeType": null,
          "count": 1,
          "isUpgrade": false,
          "isChronoBoosted": false,
          "specialAction": null
        },
        "comment": ""
      },
      {
        "supply": "48",
        "time": "4:04",
        "action": "Oracle (Chrono Boost)",
        "interpretedAction": {
          "unitType": 495,
          "upgradeType": null,
          "count": 1,
          "isUpgrade": false,
          "isChronoBoosted": true,
          "specialAction": null
        },
        "comment": ""
      },
      {
        "supply": "51",
        "time": "4:11",
        "action": "Adept x3",
        "interpretedAction": {
          "unitType": 311,
          "upgradeType": null,
          "count": 3,
          "isUpgrade": false,
          "isChronoBoosted": false,
          "specialAction": null
        },
        "comment": ""
      },
      {
        "supply": "58",
        "time": "4:17",
        "action": "Pylon",
        "interpretedAction": {
          "unitType": 60,
          "upgradeType": null,
          "count": 1,
          "isUpgrade": false,
          "isChronoBoosted": false,
          "specialAction": null
        },
        "comment": ""
      },
      {
        "supply": "58",
        "time": "4:26",
        "action": "Nexus",
        "interpretedAction": {
          "unitType": 59,
          "upgradeType": null,
          "count": 1,
          "isUpgrade": false,
          "isChronoBoosted": false,
          "specialAction": null
        },
        "comment": ""
      },
      {
        "supply": "58",
        "time": "4:36",
        "action": "Adept x3",
        "interpretedAction": {
          "unitType": 311,
          "upgradeType": null,
          "count": 3,
          "isUpgrade": false,
          "isChronoBoosted": false,
          "specialAction": null
        },
        "comment": ""
      }
    ],
    "raceMatchup": "PvT",
    "url": "https://lotv.spawningtool.com/build/168030/"
  },
  {
    "title": "HuShang's Beginner Zerg Build Order (2022)",
    "steps": [
      {
        "supply": "12",
        "time": "0:00",
        "action": "Drone",
        "interpretedAction": {
          "unitType": 104,
          "upgradeType": null,
          "count": 1,
          "isUpgrade": false,
          "isChronoBoosted": false,
          "specialAction": null
        },
        "comment": ""
      },
      {
        "supply": "13",
        "time": "0:12",
        "action": "Overlord",
        "interpretedAction": {
          "unitType": 106,
          "upgradeType": null,
          "count": 1,
          "isUpgrade": false,
          "isChronoBoosted": false,
          "specialAction": null
        },
        "comment": ""
      },
      {
        "supply": "13",
        "time": "0:18",
        "action": "Drone",
        "interpretedAction": {
          "unitType": 104,
          "upgradeType": null,
          "count": 1,
          "isUpgrade": false,
          "isChronoBoosted": false,
          "specialAction": null
        },
        "comment": ""
      },
      {
        "supply": "14",
        "time": "0:32",
        "action": "Drone x2",
        "interpretedAction": {
          "unitType": 104,
          "upgradeType": null,
          "count": 2,
          "isUpgrade": false,
          "isChronoBoosted": false,
          "specialAction": null
        },
        "comment": ""
      },
      {
        "supply": "16",
        "time": "0:48",
        "action": "Hatchery",
        "interpretedAction": {
          "unitType": 86,
          "upgradeType": null,
          "count": 1,
          "isUpgrade": false,
          "isChronoBoosted": false,
          "specialAction": null
        },
        "comment": ""
      },
      {
        "supply": "15",
        "time": "0:52",
        "action": "Drone x2",
        "interpretedAction": {
          "unitType": 104,
          "upgradeType": null,
          "count": 2,
          "isUpgrade": false,
          "isChronoBoosted": false,
          "specialAction": null
        },
        "comment": ""
      },
      {
        "supply": "17",
        "time": "0:58",
        "action": "Drone",
        "interpretedAction": {
          "unitType": 104,
          "upgradeType": null,
          "count": 1,
          "isUpgrade": false,
          "isChronoBoosted": false,
          "specialAction": null
        },
        "comment": ""
      },
      {
        "supply": "18",
        "time": "1:10",
        "action": "Extractor",
        "interpretedAction": {
          "unitType": 88,
          "upgradeType": null,
          "count": 1,
          "isUpgrade": false,
          "isChronoBoosted": false,
          "specialAction": null
        },
        "comment": ""
      },
      {
        "supply": "17",
        "time": "1:14",
        "action": "Spawning Pool",
        "interpretedAction": {
          "unitType": 89,
          "upgradeType": null,
          "count": 1,
          "isUpgrade": false,
          "isChronoBoosted": false,
          "specialAction": null
        },
        "comment": ""
      },
      {
        "supply": "17",
        "time": "1:16",
        "action": "Drone x2",
        "interpretedAction": {
          "unitType": 104,
          "upgradeType": null,
          "count": 2,
          "isUpgrade": false,
          "isChronoBoosted": false,
          "specialAction": null
        },
        "comment": ""
      },
      {
        "supply": "18",
        "time": "1:28",
        "action": "Drone",
        "interpretedAction": {
          "unitType": 104,
          "upgradeType": null,
          "count": 1,
          "isUpgrade": false,
          "isChronoBoosted": false,
          "specialAction": null
        },
        "comment": ""
      },
      {
        "supply": "20",
        "time": "1:53",
        "action": "Overlord",
        "interpretedAction": {
          "unitType": 106,
          "upgradeType": null,
          "count": 1,
          "isUpgrade": false,
          "isChronoBoosted": false,
          "specialAction": null
        },
        "comment": ""
      },
      {
        "supply": "20",
        "time": "2:01",
        "action": "Queen x2",
        "interpretedAction": {
          "unitType": 126,
          "upgradeType": null,
          "count": 2,
          "isUpgrade": false,
          "isChronoBoosted": false,
          "specialAction": null
        },
        "comment": ""
      },
      {
        "supply": "20",
        "time": "2:02",
        "action": "Zergling x4",
        "interpretedAction": {
          "unitType": 105,
          "upgradeType": null,
          "count": 4,
          "isUpgrade": false,
          "isChronoBoosted": false,
          "specialAction": null
        },
        "comment": ""
      },
      {
        "supply": "32",
        "time": "2:43",
        "action": "Overlord",
        "interpretedAction": {
          "unitType": 106,
          "upgradeType": null,
          "count": 1,
          "isUpgrade": false,
          "isChronoBoosted": false,
          "specialAction": null
        },
        "comment": ""
      },
      {
        "supply": "32",
        "time": "2:48",
        "action": "Lair",
        "interpretedAction": {
          "unitType": 100,
          "upgradeType": null,
          "count": 1,
          "isUpgrade": false,
          "isChronoBoosted": false,
          "specialAction": null
        },
        "comment": ""
      },
      {
        "supply": "36",
        "time": "3:06",
        "action": "Overlord",
        "interpretedAction": {
          "unitType": 106,
          "upgradeType": null,
          "count": 1,
          "isUpgrade": false,
          "isChronoBoosted": false,
          "specialAction": null
        },
        "comment": ""
      },
      {
        "supply": "42",
        "time": "3:14",
        "action": "Extractor x2",
        "interpretedAction": {
          "unitType": 88,
          "upgradeType": null,
          "count": 2,
          "isUpgrade": false,
          "isChronoBoosted": false,
          "specialAction": null
        },
        "comment": ""
      },
      {
        "supply": "42",
        "time": "3:16",
        "action": "Spore Crawler",
        "interpretedAction": {
          "unitType": 99,
          "upgradeType": null,
          "count": 1,
          "isUpgrade": false,
          "isChronoBoosted": false,
          "specialAction": null
        },
        "comment": ""
      },
      {
        "supply": "42",
        "time": "3:18",
        "action": "Roach Warren",
        "interpretedAction": {
          "unitType": 97,
          "upgradeType": null,
          "count": 1,
          "isUpgrade": false,
          "isChronoBoosted": false,
          "specialAction": null
        },
        "comment": ""
      },
      {
        "supply": "38",
        "time": "3:26",
        "action": "Spore Crawler",
        "interpretedAction": {
          "unitType": 99,
          "upgradeType": null,
          "count": 1,
          "isUpgrade": false,
          "isChronoBoosted": false,
          "specialAction": null
        },
        "comment": ""
      },
      {
        "supply": "47",
        "time": "3:54",
        "action": "Overlord",
        "interpretedAction": {
          "unitType": 106,
          "upgradeType": null,
          "count": 1,
          "isUpgrade": false,
          "isChronoBoosted": false,
          "specialAction": null
        },
        "comment": ""
      },
      {
        "supply": "48",
        "time": "3:55",
        "action": "Hatchery",
        "interpretedAction": {
          "unitType": 86,
          "upgradeType": null,
          "count": 1,
          "isUpgrade": false,
          "isChronoBoosted": false,
          "specialAction": null
        },
        "comment": ""
      },
      {
        "supply": "48",
        "time": "4:00",
        "action": "Glial Reconstitution",
        "interpretedAction": {
          "unitType": null,
          "upgradeType": null,
          "count": 1,
          "isUpgrade": false,
          "isChronoBoosted": false,
          "specialAction": null
        },
        "comment": ""
      },
      {
        "supply": "47",
        "time": "4:15",
        "action": "Roach x7",
        "interpretedAction": {
          "unitType": 110,
          "upgradeType": null,
          "count": 7,
          "isUpgrade": false,
          "isChronoBoosted": false,
          "specialAction": null
        },
        "comment": ""
      },
      {
        "supply": "59",
        "time": "4:21",
        "action": "Roach",
        "interpretedAction": {
          "unitType": 110,
          "upgradeType": null,
          "count": 1,
          "isUpgrade": false,
          "isChronoBoosted": false,
          "specialAction": null
        },
        "comment": ""
      },
      {
        "supply": "59",
        "time": "4:22",
        "action": "Overseer",
        "interpretedAction": {
          "unitType": 129,
          "upgradeType": null,
          "count": 1,
          "isUpgrade": false,
          "isChronoBoosted": false,
          "specialAction": null
        },
        "comment": ""
      },
      {
        "supply": "63",
        "time": "4:46",
        "action": "Roach x2",
        "interpretedAction": {
          "unitType": 110,
          "upgradeType": null,
          "count": 2,
          "isUpgrade": false,
          "isChronoBoosted": false,
          "specialAction": null
        },
        "comment": ""
      }
    ],
    "raceMatchup": "ZvX",
    "url": "https://lotv.spawningtool.com/build/163886/"
  },
  {
    "title": "HuShang's 3rax SCC Push",
    "steps": [
      {
        "supply": "6",
        "time": "0:00",
        "action": "SCV",
        "interpretedAction": {
          "unitType": 45,
          "upgradeType": null,
          "count": 1,
          "isUpgrade": false,
          "isChronoBoosted": false,
          "specialAction": null
        },
        "comment": ""
      },
      {
        "supply": "13",
        "time": "0:12",
        "action": "SCV",
        "interpretedAction": {
          "unitType": 45,
          "upgradeType": null,
          "count": 1,
          "isUpgrade": false,
          "isChronoBoosted": false,
          "specialAction": null
        },
        "comment": ""
      },
      {
        "supply": "14",
        "time": "0:17",
        "action": "Supply Depot",
        "interpretedAction": {
          "unitType": 19,
          "upgradeType": null,
          "count": 1,
          "isUpgrade": false,
          "isChronoBoosted": false,
          "specialAction": null
        },
        "comment": ""
      },
      {
        "supply": "14",
        "time": "0:24",
        "action": "SCV",
        "interpretedAction": {
          "unitType": 45,
          "upgradeType": null,
          "count": 1,
          "isUpgrade": false,
          "isChronoBoosted": false,
          "specialAction": null
        },
        "comment": ""
      },
      {
        "supply": "15",
        "time": "0:38",
        "action": "SCV",
        "interpretedAction": {
          "unitType": 45,
          "upgradeType": null,
          "count": 1,
          "isUpgrade": false,
          "isChronoBoosted": false,
          "specialAction": null
        },
        "comment": ""
      },
      {
        "supply": "15",
        "time": "0:39",
        "action": "Barracks",
        "interpretedAction": {
          "unitType": 21,
          "upgradeType": null,
          "count": 1,
          "isUpgrade": false,
          "isChronoBoosted": false,
          "specialAction": null
        },
        "comment": ""
      },
      {
        "supply": "16",
        "time": "0:43",
        "action": "Refinery",
        "interpretedAction": {
          "unitType": 20,
          "upgradeType": null,
          "count": 1,
          "isUpgrade": false,
          "isChronoBoosted": false,
          "specialAction": null
        },
        "comment": ""
      },
      {
        "supply": "16",
        "time": "0:50",
        "action": "SCV",
        "interpretedAction": {
          "unitType": 45,
          "upgradeType": null,
          "count": 1,
          "isUpgrade": false,
          "isChronoBoosted": false,
          "specialAction": null
        },
        "comment": ""
      },
      {
        "supply": "17",
        "time": "1:02",
        "action": "SCV",
        "interpretedAction": {
          "unitType": 45,
          "upgradeType": null,
          "count": 1,
          "isUpgrade": false,
          "isChronoBoosted": false,
          "specialAction": null
        },
        "comment": ""
      },
      {
        "supply": "18",
        "time": "1:15",
        "action": "SCV",
        "interpretedAction": {
          "unitType": 45,
          "upgradeType": null,
          "count": 1,
          "isUpgrade": false,
          "isChronoBoosted": false,
          "specialAction": null
        },
        "comment": ""
      },
      {
        "supply": "19",
        "time": "1:27",
        "action": "Marine",
        "interpretedAction": {
          "unitType": 48,
          "upgradeType": null,
          "count": 1,
          "isUpgrade": false,
          "isChronoBoosted": false,
          "specialAction": null
        },
        "comment": ""
      },
      {
        "supply": "19",
        "time": "1:28",
        "action": "Orbital Command",
        "interpretedAction": {
          "unitType": 132,
          "upgradeType": null,
          "count": 1,
          "isUpgrade": false,
          "isChronoBoosted": false,
          "specialAction": null
        },
        "comment": ""
      },
      {
        "supply": "20",
        "time": "1:42",
        "action": "Command Center",
        "interpretedAction": {
          "unitType": 18,
          "upgradeType": null,
          "count": 1,
          "isUpgrade": false,
          "isChronoBoosted": false,
          "specialAction": null
        },
        "comment": ""
      },
      {
        "supply": "20",
        "time": "1:45",
        "action": "Barracks Reactor",
        "interpretedAction": {
          "unitType": 38,
          "upgradeType": null,
          "count": 1,
          "isUpgrade": false,
          "isChronoBoosted": false,
          "specialAction": null
        },
        "comment": ""
      },
      {
        "supply": "20",
        "time": "1:53",
        "action": "SCV",
        "interpretedAction": {
          "unitType": 45,
          "upgradeType": null,
          "count": 1,
          "isUpgrade": false,
          "isChronoBoosted": false,
          "specialAction": null
        },
        "comment": ""
      },
      {
        "supply": "21",
        "time": "1:57",
        "action": "Supply Depot",
        "interpretedAction": {
          "unitType": 19,
          "upgradeType": null,
          "count": 1,
          "isUpgrade": false,
          "isChronoBoosted": false,
          "specialAction": null
        },
        "comment": ""
      },
      {
        "supply": "21",
        "time": "2:05",
        "action": "SCV",
        "interpretedAction": {
          "unitType": 45,
          "upgradeType": null,
          "count": 1,
          "isUpgrade": false,
          "isChronoBoosted": false,
          "specialAction": null
        },
        "comment": ""
      },
      {
        "supply": "22",
        "time": "2:17",
        "action": "SCV",
        "interpretedAction": {
          "unitType": 45,
          "upgradeType": null,
          "count": 1,
          "isUpgrade": false,
          "isChronoBoosted": false,
          "specialAction": null
        },
        "comment": ""
      },
      {
        "supply": "22",
        "time": "2:20",
        "action": "Barracks x2",
        "interpretedAction": {
          "unitType": 21,
          "upgradeType": null,
          "count": 2,
          "isUpgrade": false,
          "isChronoBoosted": false,
          "specialAction": null
        },
        "comment": ""
      },
      {
        "supply": "23",
        "time": "2:24",
        "action": "Marine x2",
        "interpretedAction": {
          "unitType": 48,
          "upgradeType": null,
          "count": 2,
          "isUpgrade": false,
          "isChronoBoosted": false,
          "specialAction": null
        },
        "comment": ""
      },
      {
        "supply": "26",
        "time": "2:42",
        "action": "Marine x2",
        "interpretedAction": {
          "unitType": 48,
          "upgradeType": null,
          "count": 2,
          "isUpgrade": false,
          "isChronoBoosted": false,
          "specialAction": null
        },
        "comment": ""
      },
      {
        "supply": "29",
        "time": "2:55",
        "action": "Orbital Command",
        "interpretedAction": {
          "unitType": 132,
          "upgradeType": null,
          "count": 1,
          "isUpgrade": false,
          "isChronoBoosted": false,
          "specialAction": null
        },
        "comment": ""
      },
      {
        "supply": "30",
        "time": "3:00",
        "action": "Marine x2",
        "interpretedAction": {
          "unitType": 48,
          "upgradeType": null,
          "count": 2,
          "isUpgrade": false,
          "isChronoBoosted": false,
          "specialAction": null
        },
        "comment": ""
      },
      {
        "supply": "32",
        "time": "3:11",
        "action": "Barracks Tech Lab x2",
        "interpretedAction": {
          "unitType": 37,
          "upgradeType": null,
          "count": 2,
          "isUpgrade": false,
          "isChronoBoosted": false,
          "specialAction": null
        },
        "comment": ""
      },
      {
        "supply": "33",
        "time": "3:21",
        "action": "Supply Depot",
        "interpretedAction": {
          "unitType": 19,
          "upgradeType": null,
          "count": 1,
          "isUpgrade": false,
          "isChronoBoosted": false,
          "specialAction": null
        },
        "comment": ""
      },
      {
        "supply": "33",
        "time": "3:25",
        "action": "Marine",
        "interpretedAction": {
          "unitType": 48,
          "upgradeType": null,
          "count": 1,
          "isUpgrade": false,
          "isChronoBoosted": false,
          "specialAction": null
        },
        "comment": ""
      },
      {
        "supply": "37",
        "time": "3:30",
        "action": "Stimpack, Concussive Shells",
        "interpretedAction": {
          "unitType": null,
          "upgradeType": null,
          "count": 1,
          "isUpgrade": false,
          "isChronoBoosted": false,
          "specialAction": null
        },
        "comment": ""
      },
      {
        "supply": "37",
        "time": "3:30",
        "action": "Stimpack, Concussive Shells",
        "interpretedAction": {
          "unitType": null,
          "upgradeType": null,
          "count": 1,
          "isUpgrade": false,
          "isChronoBoosted": false,
          "specialAction": null
        },
        "comment": ""
      },
      {
        "supply": "37",
        "time": "3:32",
        "action": "Marine x2",
        "interpretedAction": {
          "unitType": 48,
          "upgradeType": null,
          "count": 2,
          "isUpgrade": false,
          "isChronoBoosted": false,
          "specialAction": null
        },
        "comment": ""
      },
      {
        "supply": "41",
        "time": "3:46",
        "action": "Supply Depot, Refinery",
        "interpretedAction": {
          "unitType": 19,
          "upgradeType": null,
          "count": 1,
          "isUpgrade": false,
          "isChronoBoosted": false,
          "specialAction": null
        },
        "comment": ""
      },
      {
        "supply": "41",
        "time": "3:46",
        "action": "Supply Depot, Refinery",
        "interpretedAction": {
          "unitType": 20,
          "upgradeType": null,
          "count": 1,
          "isUpgrade": false,
          "isChronoBoosted": false,
          "specialAction": null
        },
        "comment": ""
      },
      {
        "supply": "43",
        "time": "3:50",
        "action": "Marauder x2",
        "interpretedAction": {
          "unitType": 51,
          "upgradeType": null,
          "count": 2,
          "isUpgrade": false,
          "isChronoBoosted": false,
          "specialAction": null
        },
        "comment": ""
      },
      {
        "supply": "49",
        "time": "4:02",
        "action": "Engineering Bay",
        "interpretedAction": {
          "unitType": 22,
          "upgradeType": null,
          "count": 1,
          "isUpgrade": false,
          "isChronoBoosted": false,
          "specialAction": null
        },
        "comment": ""
      },
      {
        "supply": "51",
        "time": "4:05",
        "action": "Supply Depot",
        "interpretedAction": {
          "unitType": 19,
          "upgradeType": null,
          "count": 1,
          "isUpgrade": false,
          "isChronoBoosted": false,
          "specialAction": null
        },
        "comment": ""
      },
      {
        "supply": "53",
        "time": "4:13",
        "action": "Combat Shield",
        "interpretedAction": {
          "unitType": null,
          "upgradeType": null,
          "count": 1,
          "isUpgrade": false,
          "isChronoBoosted": false,
          "specialAction": null
        },
        "comment": ""
      },
      {
        "supply": "63",
        "time": "4:43",
        "action": "Factory",
        "interpretedAction": {
          "unitType": 27,
          "upgradeType": null,
          "count": 1,
          "isUpgrade": false,
          "isChronoBoosted": false,
          "specialAction": null
        },
        "comment": ""
      },
      {
        "supply": "65",
        "time": "4:49",
        "action": "Missile Turret",
        "interpretedAction": {
          "unitType": 23,
          "upgradeType": null,
          "count": 1,
          "isUpgrade": false,
          "isChronoBoosted": false,
          "specialAction": null
        },
        "comment": ""
      },
      {
        "supply": "65",
        "time": "4:53",
        "action": "Terran Infantry Weapons Level 1",
        "interpretedAction": {
          "unitType": null,
          "upgradeType": null,
          "count": 1,
          "isUpgrade": false,
          "isChronoBoosted": false,
          "specialAction": null
        },
        "comment": ""
      },
      {
        "supply": "65",
        "time": "4:58",
        "action": "Command Center",
        "interpretedAction": {
          "unitType": 18,
          "upgradeType": null,
          "count": 1,
          "isUpgrade": false,
          "isChronoBoosted": false,
          "specialAction": null
        },
        "comment": ""
      },
      {
        "supply": "78",
        "time": "5:25",
        "action": "Refinery x2",
        "interpretedAction": {
          "unitType": 20,
          "upgradeType": null,
          "count": 2,
          "isUpgrade": false,
          "isChronoBoosted": false,
          "specialAction": null
        },
        "comment": ""
      },
      {
        "supply": "78",
        "time": "5:28",
        "action": "Starport, Factory Reactor",
        "interpretedAction": {
          "unitType": 28,
          "upgradeType": null,
          "count": 1,
          "isUpgrade": false,
          "isChronoBoosted": false,
          "specialAction": null
        },
        "comment": ""
      },
      {
        "supply": "78",
        "time": "5:28",
        "action": "Starport, Factory Reactor",
        "interpretedAction": {
          "unitType": 40,
          "upgradeType": null,
          "count": 1,
          "isUpgrade": false,
          "isChronoBoosted": false,
          "specialAction": null
        },
        "comment": ""
      },
      {
        "supply": "78",
        "time": "5:41",
        "action": "Marauder x2",
        "interpretedAction": {
          "unitType": 51,
          "upgradeType": null,
          "count": 2,
          "isUpgrade": false,
          "isChronoBoosted": false,
          "specialAction": null
        },
        "comment": ""
      },
      {
        "supply": "86",
        "time": "5:47",
        "action": "Barracks x2",
        "interpretedAction": {
          "unitType": 21,
          "upgradeType": null,
          "count": 2,
          "isUpgrade": false,
          "isChronoBoosted": false,
          "specialAction": null
        },
        "comment": ""
      },
      {
        "supply": "85",
        "time": "6:04",
        "action": "Marauder x2",
        "interpretedAction": {
          "unitType": 51,
          "upgradeType": null,
          "count": 2,
          "isUpgrade": false,
          "isChronoBoosted": false,
          "specialAction": null
        },
        "comment": ""
      },
      {
        "supply": "91",
        "time": "6:15",
        "action": "Medivac x2",
        "interpretedAction": {
          "unitType": 54,
          "upgradeType": null,
          "count": 2,
          "isUpgrade": false,
          "isChronoBoosted": false,
          "specialAction": null
        },
        "comment": ""
      },
      {
        "supply": "97",
        "time": "6:22",
        "action": "Factory Reactor",
        "interpretedAction": {
          "unitType": 40,
          "upgradeType": null,
          "count": 1,
          "isUpgrade": false,
          "isChronoBoosted": false,
          "specialAction": null
        },
        "comment": ""
      },
      {
        "supply": "96",
        "time": "6:28",
        "action": "Marauder x2",
        "interpretedAction": {
          "unitType": 51,
          "upgradeType": null,
          "count": 2,
          "isUpgrade": false,
          "isChronoBoosted": false,
          "specialAction": null
        },
        "comment": ""
      },
      {
        "supply": "96",
        "time": "6:32",
        "action": "Orbital Command",
        "interpretedAction": {
          "unitType": 132,
          "upgradeType": null,
          "count": 1,
          "isUpgrade": false,
          "isChronoBoosted": false,
          "specialAction": null
        },
        "comment": ""
      },
      {
        "supply": "102",
        "time": "6:36",
        "action": "Barracks Reactor, Barracks Tech Lab",
        "interpretedAction": {
          "unitType": 38,
          "upgradeType": null,
          "count": 1,
          "isUpgrade": false,
          "isChronoBoosted": false,
          "specialAction": null
        },
        "comment": ""
      },
      {
        "supply": "102",
        "time": "6:36",
        "action": "Barracks Reactor, Barracks Tech Lab",
        "interpretedAction": {
          "unitType": 37,
          "upgradeType": null,
          "count": 1,
          "isUpgrade": false,
          "isChronoBoosted": false,
          "specialAction": null
        },
        "comment": ""
      },
      {
        "supply": "102",
        "time": "6:45",
        "action": "Medivac x2",
        "interpretedAction": {
          "unitType": 54,
          "upgradeType": null,
          "count": 2,
          "isUpgrade": false,
          "isChronoBoosted": false,
          "specialAction": null
        },
        "comment": ""
      },
      {
        "supply": "108",
        "time": "6:50",
        "action": "Marauder x2",
        "interpretedAction": {
          "unitType": 51,
          "upgradeType": null,
          "count": 2,
          "isUpgrade": false,
          "isChronoBoosted": false,
          "specialAction": null
        },
        "comment": ""
      },
      {
        "supply": "115",
        "time": "7:06",
        "action": "Bunker",
        "interpretedAction": {
          "unitType": 24,
          "upgradeType": null,
          "count": 1,
          "isUpgrade": false,
          "isChronoBoosted": false,
          "specialAction": null
        },
        "comment": ""
      },
      {
        "supply": "115",
        "time": "7:11",
        "action": "Widow Mine x2",
        "interpretedAction": {
          "unitType": 498,
          "upgradeType": null,
          "count": 2,
          "isUpgrade": false,
          "isChronoBoosted": false,
          "specialAction": null
        },
        "comment": ""
      },
      {
        "supply": "115",
        "time": "7:15",
        "action": "Medivac x2",
        "interpretedAction": {
          "unitType": 54,
          "upgradeType": null,
          "count": 2,
          "isUpgrade": false,
          "isChronoBoosted": false,
          "specialAction": null
        },
        "comment": ""
      },
      {
        "supply": "146",
        "time": "7:45",
        "action": "Refinery x2",
        "interpretedAction": {
          "unitType": 20,
          "upgradeType": null,
          "count": 2,
          "isUpgrade": false,
          "isChronoBoosted": false,
          "specialAction": null
        },
        "comment": ""
      },
      {
        "supply": "146",
        "time": "7:52",
        "action": "Widow Mine x2",
        "interpretedAction": {
          "unitType": 498,
          "upgradeType": null,
          "count": 2,
          "isUpgrade": false,
          "isChronoBoosted": false,
          "specialAction": null
        },
        "comment": ""
      },
      {
        "supply": "146",
        "time": "7:57",
        "action": "Medivac x2",
        "interpretedAction": {
          "unitType": 54,
          "upgradeType": null,
          "count": 2,
          "isUpgrade": false,
          "isChronoBoosted": false,
          "specialAction": null
        },
        "comment": ""
      },
      {
        "supply": "163",
        "time": "8:12",
        "action": "Command Center",
        "interpretedAction": {
          "unitType": 18,
          "upgradeType": null,
          "count": 1,
          "isUpgrade": false,
          "isChronoBoosted": false,
          "specialAction": null
        },
        "comment": ""
      }
    ],
    "raceMatchup": "TvP",
    "url": "https://lotv.spawningtool.com/build/158142/"
  },
  {
    "title": "Beginner Friendly Zerg Build Order (vs all races)",
    "steps": [
      {
        "supply": "13",
        "time": "0:12",
        "action": "Overlord",
        "interpretedAction": {
          "unitType": 106,
          "upgradeType": null,
          "count": 1,
          "isUpgrade": false,
          "isChronoBoosted": false,
          "specialAction": null
        },
        "comment": ""
      },
      {
        "supply": "16",
        "time": "0:48",
        "action": "Hatchery",
        "interpretedAction": {
          "unitType": 86,
          "upgradeType": null,
          "count": 1,
          "isUpgrade": false,
          "isChronoBoosted": false,
          "specialAction": null
        },
        "comment": ""
      },
      {
        "supply": "18",
        "time": "1:08",
        "action": "Extractor",
        "interpretedAction": {
          "unitType": 88,
          "upgradeType": null,
          "count": 1,
          "isUpgrade": false,
          "isChronoBoosted": false,
          "specialAction": null
        },
        "comment": ""
      },
      {
        "supply": "17",
        "time": "1:13",
        "action": "Spawning Pool",
        "interpretedAction": {
          "unitType": 89,
          "upgradeType": null,
          "count": 1,
          "isUpgrade": false,
          "isChronoBoosted": false,
          "specialAction": null
        },
        "comment": ""
      },
      {
        "supply": "19",
        "time": "1:39",
        "action": "Overlord",
        "interpretedAction": {
          "unitType": 106,
          "upgradeType": null,
          "count": 1,
          "isUpgrade": false,
          "isChronoBoosted": false,
          "specialAction": null
        },
        "comment": ""
      },
      {
        "supply": "19",
        "time": "2:00",
        "action": "Queen x2",
        "interpretedAction": {
          "unitType": 126,
          "upgradeType": null,
          "count": 2,
          "isUpgrade": false,
          "isChronoBoosted": false,
          "specialAction": null
        },
        "comment": ""
      },
      {
        "supply": "24",
        "time": "2:01",
        "action": "Zergling x6",
        "interpretedAction": {
          "unitType": 105,
          "upgradeType": null,
          "count": 6,
          "isUpgrade": false,
          "isChronoBoosted": false,
          "specialAction": null
        },
        "comment": ""
      },
      {
        "supply": "30",
        "time": "2:32",
        "action": "Overlord",
        "interpretedAction": {
          "unitType": 106,
          "upgradeType": null,
          "count": 1,
          "isUpgrade": false,
          "isChronoBoosted": false,
          "specialAction": null
        },
        "comment": ""
      },
      {
        "supply": "30",
        "time": "2:35",
        "action": "Queen",
        "interpretedAction": {
          "unitType": 126,
          "upgradeType": null,
          "count": 1,
          "isUpgrade": false,
          "isChronoBoosted": false,
          "specialAction": null
        },
        "comment": ""
      },
      {
        "supply": "33",
        "time": "2:40",
        "action": "Lair",
        "interpretedAction": {
          "unitType": 100,
          "upgradeType": null,
          "count": 1,
          "isUpgrade": false,
          "isChronoBoosted": false,
          "specialAction": null
        },
        "comment": ""
      },
      {
        "supply": "37",
        "time": "3:02",
        "action": "Evolution Chamber",
        "interpretedAction": {
          "unitType": 90,
          "upgradeType": null,
          "count": 1,
          "isUpgrade": false,
          "isChronoBoosted": false,
          "specialAction": null
        },
        "comment": ""
      },
      {
        "supply": "37",
        "time": "3:04",
        "action": "Roach Warren",
        "interpretedAction": {
          "unitType": 97,
          "upgradeType": null,
          "count": 1,
          "isUpgrade": false,
          "isChronoBoosted": false,
          "specialAction": null
        },
        "comment": ""
      },
      {
        "supply": "44",
        "time": "3:27",
        "action": "Overlord",
        "interpretedAction": {
          "unitType": 106,
          "upgradeType": null,
          "count": 1,
          "isUpgrade": false,
          "isChronoBoosted": false,
          "specialAction": null
        },
        "comment": ""
      },
      {
        "supply": "44",
        "time": "3:33",
        "action": "Zerg Missile Weapons Level 1",
        "interpretedAction": {
          "unitType": null,
          "upgradeType": null,
          "count": 1,
          "isUpgrade": false,
          "isChronoBoosted": false,
          "specialAction": null
        },
        "comment": ""
      },
      {
        "supply": "52",
        "time": "3:50",
        "action": "Extractor x2",
        "interpretedAction": {
          "unitType": 88,
          "upgradeType": null,
          "count": 2,
          "isUpgrade": false,
          "isChronoBoosted": false,
          "specialAction": null
        },
        "comment": ""
      },
      {
        "supply": "50",
        "time": "4:01",
        "action": "Overlord x2",
        "interpretedAction": {
          "unitType": 106,
          "upgradeType": null,
          "count": 2,
          "isUpgrade": false,
          "isChronoBoosted": false,
          "specialAction": null
        },
        "comment": ""
      },
      {
        "supply": "50",
        "time": "4:06",
        "action": "Glial Reconstitution",
        "interpretedAction": {
          "unitType": null,
          "upgradeType": null,
          "count": 1,
          "isUpgrade": false,
          "isChronoBoosted": false,
          "specialAction": null
        },
        "comment": ""
      },
      {
        "supply": "50",
        "time": "4:20",
        "action": "Roach x8",
        "interpretedAction": {
          "unitType": 110,
          "upgradeType": null,
          "count": 8,
          "isUpgrade": false,
          "isChronoBoosted": false,
          "specialAction": null
        },
        "comment": ""
      }
    ],
    "raceMatchup": "ZvX",
    "url": "https://lotv.spawningtool.com/build/142749/"
  },
  {
    "title": "Voidray into Adept-Glaives",
    "steps": [
      {
        "supply": "12",
        "time": "0:00",
        "action": "Probe",
        "interpretedAction": {
          "unitType": 84,
          "upgradeType": null,
          "count": 1,
          "isUpgrade": false,
          "isChronoBoosted": false,
          "specialAction": null
        },
        "comment": ""
      },
      {
        "supply": "13",
        "time": "0:12",
        "action": "Probe",
        "interpretedAction": {
          "unitType": 84,
          "upgradeType": null,
          "count": 1,
          "isUpgrade": false,
          "isChronoBoosted": false,
          "specialAction": null
        },
        "comment": ""
      },
      {
        "supply": "14",
        "time": "0:20",
        "action": "Pylon",
        "interpretedAction": {
          "unitType": 60,
          "upgradeType": null,
          "count": 1,
          "isUpgrade": false,
          "isChronoBoosted": false,
          "specialAction": null
        },
        "comment": ""
      },
      {
        "supply": "14",
        "time": "0:24",
        "action": "Probe",
        "interpretedAction": {
          "unitType": 84,
          "upgradeType": null,
          "count": 1,
          "isUpgrade": false,
          "isChronoBoosted": false,
          "specialAction": null
        },
        "comment": ""
      },
      {
        "supply": "15",
        "time": "0:38",
        "action": "Probe (Chrono Boost)",
        "interpretedAction": {
          "unitType": 84,
          "upgradeType": null,
          "count": 1,
          "isUpgrade": false,
          "isChronoBoosted": true,
          "specialAction": null
        },
        "comment": ""
      },
      {
        "supply": "15",
        "time": "0:40",
        "action": "Gateway",
        "interpretedAction": {
          "unitType": 62,
          "upgradeType": null,
          "count": 1,
          "isUpgrade": false,
          "isChronoBoosted": false,
          "specialAction": null
        },
        "comment": ""
      },
      {
        "supply": "16",
        "time": "0:45",
        "action": "Assimilator",
        "interpretedAction": {
          "unitType": 61,
          "upgradeType": null,
          "count": 1,
          "isUpgrade": false,
          "isChronoBoosted": false,
          "specialAction": null
        },
        "comment": ""
      },
      {
        "supply": "16",
        "time": "0:50",
        "action": "Probe (Chrono Boost)",
        "interpretedAction": {
          "unitType": 84,
          "upgradeType": null,
          "count": 1,
          "isUpgrade": false,
          "isChronoBoosted": true,
          "specialAction": null
        },
        "comment": ""
      },
      {
        "supply": "17",
        "time": "0:59",
        "action": "Probe (Chrono Boost)",
        "interpretedAction": {
          "unitType": 84,
          "upgradeType": null,
          "count": 1,
          "isUpgrade": false,
          "isChronoBoosted": true,
          "specialAction": null
        },
        "comment": ""
      },
      {
        "supply": "18",
        "time": "1:04",
        "action": "Probe (Chrono Boost)",
        "interpretedAction": {
          "unitType": 84,
          "upgradeType": null,
          "count": 1,
          "isUpgrade": false,
          "isChronoBoosted": true,
          "specialAction": null
        },
        "comment": ""
      },
      {
        "supply": "19",
        "time": "1:16",
        "action": "Probe (Chrono Boost)",
        "interpretedAction": {
          "unitType": 84,
          "upgradeType": null,
          "count": 1,
          "isUpgrade": false,
          "isChronoBoosted": true,
          "specialAction": null
        },
        "comment": ""
      },
      {
        "supply": "20",
        "time": "1:22",
        "action": "Probe (Chrono Boost)",
        "interpretedAction": {
          "unitType": 84,
          "upgradeType": null,
          "count": 1,
          "isUpgrade": false,
          "isChronoBoosted": true,
          "specialAction": null
        },
        "comment": ""
      },
      {
        "supply": "21",
        "time": "1:27",
        "action": "Nexus",
        "interpretedAction": {
          "unitType": 59,
          "upgradeType": null,
          "count": 1,
          "isUpgrade": false,
          "isChronoBoosted": false,
          "specialAction": null
        },
        "comment": ""
      },
      {
        "supply": "21",
        "time": "1:37",
        "action": "Cybernetics Core",
        "interpretedAction": {
          "unitType": 72,
          "upgradeType": null,
          "count": 1,
          "isUpgrade": false,
          "isChronoBoosted": false,
          "specialAction": null
        },
        "comment": ""
      },
      {
        "supply": "21",
        "time": "1:42",
        "action": "Assimilator",
        "interpretedAction": {
          "unitType": 61,
          "upgradeType": null,
          "count": 1,
          "isUpgrade": false,
          "isChronoBoosted": false,
          "specialAction": null
        },
        "comment": ""
      },
      {
        "supply": "21",
        "time": "1:45",
        "action": "Probe",
        "interpretedAction": {
          "unitType": 84,
          "upgradeType": null,
          "count": 1,
          "isUpgrade": false,
          "isChronoBoosted": false,
          "specialAction": null
        },
        "comment": ""
      },
      {
        "supply": "22",
        "time": "1:55",
        "action": "Pylon",
        "interpretedAction": {
          "unitType": 60,
          "upgradeType": null,
          "count": 1,
          "isUpgrade": false,
          "isChronoBoosted": false,
          "specialAction": null
        },
        "comment": ""
      },
      {
        "supply": "23",
        "time": "2:11",
        "action": "Adept (Chrono Boost)",
        "interpretedAction": {
          "unitType": 311,
          "upgradeType": null,
          "count": 1,
          "isUpgrade": false,
          "isChronoBoosted": true,
          "specialAction": null
        },
        "comment": ""
      },
      {
        "supply": "26",
        "time": "2:18",
        "action": "Stargate",
        "interpretedAction": {
          "unitType": 67,
          "upgradeType": null,
          "count": 1,
          "isUpgrade": false,
          "isChronoBoosted": false,
          "specialAction": null
        },
        "comment": ""
      },
      {
        "supply": "26",
        "time": "2:26",
        "action": "Warp Gate",
        "interpretedAction": {
          "unitType": 133,
          "upgradeType": null,
          "count": 1,
          "isUpgrade": false,
          "isChronoBoosted": false,
          "specialAction": null
        },
        "comment": ""
      },
      {
        "supply": "27",
        "time": "2:34",
        "action": "Adept",
        "interpretedAction": {
          "unitType": 311,
          "upgradeType": null,
          "count": 1,
          "isUpgrade": false,
          "isChronoBoosted": false,
          "specialAction": null
        },
        "comment": ""
      },
      {
        "supply": "33",
        "time": "3:05",
        "action": "Void Ray (Chrono Boost)",
        "interpretedAction": {
          "unitType": 80,
          "upgradeType": null,
          "count": 1,
          "isUpgrade": false,
          "isChronoBoosted": true,
          "specialAction": null
        },
        "comment": ""
      },
      {
        "supply": "41",
        "time": "3:23",
        "action": "Twilight Council",
        "interpretedAction": {
          "unitType": 65,
          "upgradeType": null,
          "count": 1,
          "isUpgrade": false,
          "isChronoBoosted": false,
          "specialAction": null
        },
        "comment": ""
      },
      {
        "supply": "42",
        "time": "3:30",
        "action": "Gateway",
        "interpretedAction": {
          "unitType": 62,
          "upgradeType": null,
          "count": 1,
          "isUpgrade": false,
          "isChronoBoosted": false,
          "specialAction": null
        },
        "comment": ""
      },
      {
        "supply": "45",
        "time": "3:46",
        "action": "Gateway x2",
        "interpretedAction": {
          "unitType": 62,
          "upgradeType": null,
          "count": 2,
          "isUpgrade": false,
          "isChronoBoosted": false,
          "specialAction": null
        },
        "comment": ""
      },
      {
        "supply": "45",
        "time": "3:50",
        "action": "Resonating Glaives (Chrono Boost)",
        "interpretedAction": {
          "unitType": null,
          "upgradeType": null,
          "count": 1,
          "isUpgrade": false,
          "isChronoBoosted": true,
          "specialAction": null
        },
        "comment": ""
      },
      {
        "supply": "45",
        "time": "3:51",
        "action": "Pylon",
        "interpretedAction": {
          "unitType": 60,
          "upgradeType": null,
          "count": 1,
          "isUpgrade": false,
          "isChronoBoosted": false,
          "specialAction": null
        },
        "comment": ""
      },
      {
        "supply": "46",
        "time": "4:03",
        "action": "Nexus",
        "interpretedAction": {
          "unitType": 59,
          "upgradeType": null,
          "count": 1,
          "isUpgrade": false,
          "isChronoBoosted": false,
          "specialAction": null
        },
        "comment": ""
      },
      {
        "supply": "48",
        "time": "4:13",
        "action": "Pylon",
        "interpretedAction": {
          "unitType": 60,
          "upgradeType": null,
          "count": 1,
          "isUpgrade": false,
          "isChronoBoosted": false,
          "specialAction": null
        },
        "comment": ""
      },
      {
        "supply": "48",
        "time": "4:21",
        "action": "Adept x2",
        "interpretedAction": {
          "unitType": 311,
          "upgradeType": null,
          "count": 2,
          "isUpgrade": false,
          "isChronoBoosted": false,
          "specialAction": null
        },
        "comment": ""
      },
      {
        "supply": "52",
        "time": "4:24",
        "action": "Pylon",
        "interpretedAction": {
          "unitType": 60,
          "upgradeType": null,
          "count": 1,
          "isUpgrade": false,
          "isChronoBoosted": false,
          "specialAction": null
        },
        "comment": ""
      },
      {
        "supply": "56",
        "time": "4:46",
        "action": "Adept x4",
        "interpretedAction": {
          "unitType": 311,
          "upgradeType": null,
          "count": 4,
          "isUpgrade": false,
          "isChronoBoosted": false,
          "specialAction": null
        },
        "comment": ""
      },
      {
        "supply": "56",
        "time": "4:52",
        "action": "Assimilator x2",
        "interpretedAction": {
          "unitType": 61,
          "upgradeType": null,
          "count": 2,
          "isUpgrade": false,
          "isChronoBoosted": false,
          "specialAction": null
        },
        "comment": ""
      },
      {
        "supply": "66",
        "time": "5:06",
        "action": "Adept x2",
        "interpretedAction": {
          "unitType": 311,
          "upgradeType": null,
          "count": 2,
          "isUpgrade": false,
          "isChronoBoosted": false,
          "specialAction": null
        },
        "comment": ""
      },
      {
        "supply": "79",
        "time": "5:24",
        "action": "Robotics Facility",
        "interpretedAction": {
          "unitType": 71,
          "upgradeType": null,
          "count": 1,
          "isUpgrade": false,
          "isChronoBoosted": false,
          "specialAction": null
        },
        "comment": ""
      },
      {
        "supply": "79",
        "time": "5:26",
        "action": "Forge",
        "interpretedAction": {
          "unitType": 63,
          "upgradeType": null,
          "count": 1,
          "isUpgrade": false,
          "isChronoBoosted": false,
          "specialAction": null
        },
        "comment": ""
      },
      {
        "supply": "82",
        "time": "5:36",
        "action": "Sentry x4",
        "interpretedAction": {
          "unitType": 77,
          "upgradeType": null,
          "count": 4,
          "isUpgrade": false,
          "isChronoBoosted": false,
          "specialAction": null
        },
        "comment": ""
      },
      {
        "supply": "93",
        "time": "5:58",
        "action": "Shield Battery",
        "interpretedAction": {
          "unitType": 1910,
          "upgradeType": null,
          "count": 1,
          "isUpgrade": false,
          "isChronoBoosted": false,
          "specialAction": null
        },
        "comment": ""
      }
    ],
    "raceMatchup": "PvZ",
    "url": "https://lotv.spawningtool.com/build/182635/"
  },
  {
    "title": "Zerg banel",
    "steps": [
      {
        "supply": "14",
        "time": "",
        "action": "Drone",
        "interpretedAction": {
          "unitType": 104,
          "upgradeType": null,
          "count": 1,
          "isUpgrade": false,
          "isChronoBoosted": false,
          "specialAction": null
        },
        "comment": "Scouting drone"
      },
      {
        "supply": "17",
        "time": "",
        "action": "Hatchery",
        "interpretedAction": {
          "unitType": 86,
          "upgradeType": null,
          "count": 1,
          "isUpgrade": false,
          "isChronoBoosted": false,
          "specialAction": null
        },
        "comment": ""
      },
      {
        "supply": "18",
        "time": "",
        "action": "Extractor",
        "interpretedAction": {
          "unitType": 88,
          "upgradeType": null,
          "count": 1,
          "isUpgrade": false,
          "isChronoBoosted": false,
          "specialAction": null
        },
        "comment": ""
      },
      {
        "supply": "17",
        "time": "",
        "action": "Spawning Pool",
        "interpretedAction": {
          "unitType": 89,
          "upgradeType": null,
          "count": 1,
          "isUpgrade": false,
          "isChronoBoosted": false,
          "specialAction": null
        },
        "comment": ""
      },
      {
        "supply": "19",
        "time": "",
        "action": "Metabolic Boost",
        "interpretedAction": {
          "unitType": null,
          "upgradeType": null,
          "count": 1,
          "isUpgrade": false,
          "isChronoBoosted": false,
          "specialAction": null
        },
        "comment": ""
      },
      {
        "supply": "32",
        "time": "",
        "action": "Hatchery",
        "interpretedAction": {
          "unitType": 86,
          "upgradeType": null,
          "count": 1,
          "isUpgrade": false,
          "isChronoBoosted": false,
          "specialAction": null
        },
        "comment": "3rd"
      },
      {
        "supply": "31",
        "time": "",
        "action": "Overlord",
        "interpretedAction": {
          "unitType": 106,
          "upgradeType": null,
          "count": 1,
          "isUpgrade": false,
          "isChronoBoosted": false,
          "specialAction": null
        },
        "comment": ""
      },
      {
        "supply": "31",
        "time": "",
        "action": "Queen",
        "interpretedAction": {
          "unitType": 126,
          "upgradeType": null,
          "count": 1,
          "isUpgrade": false,
          "isChronoBoosted": false,
          "specialAction": null
        },
        "comment": ""
      },
      {
        "supply": "",
        "time": "3:30",
        "action": "Extractor",
        "interpretedAction": {
          "unitType": 88,
          "upgradeType": null,
          "count": 1,
          "isUpgrade": false,
          "isChronoBoosted": false,
          "specialAction": null
        },
        "comment": "Back on gas"
      },
      {
        "supply": "",
        "time": "4:00",
        "action": "Overlord",
        "interpretedAction": {
          "unitType": 106,
          "upgradeType": null,
          "count": 1,
          "isUpgrade": false,
          "isChronoBoosted": false,
          "specialAction": null
        },
        "comment": "Send over lord in"
      },
      {
        "supply": "48",
        "time": "4:15",
        "action": "Baneling Nest",
        "interpretedAction": {
          "unitType": 96,
          "upgradeType": null,
          "count": 1,
          "isUpgrade": false,
          "isChronoBoosted": false,
          "specialAction": null
        },
        "comment": ""
      },
      {
        "supply": "48",
        "time": "4:17",
        "action": "Extractor",
        "interpretedAction": {
          "unitType": 88,
          "upgradeType": null,
          "count": 1,
          "isUpgrade": false,
          "isChronoBoosted": false,
          "specialAction": null
        },
        "comment": "2nd"
      },
      {
        "supply": "48",
        "time": "4:24",
        "action": "Queen x3",
        "interpretedAction": {
          "unitType": 126,
          "upgradeType": null,
          "count": 3,
          "isUpgrade": false,
          "isChronoBoosted": false,
          "specialAction": null
        },
        "comment": ""
      },
      {
        "supply": "50",
        "time": "4:28",
        "action": "Zergling x9",
        "interpretedAction": {
          "unitType": 105,
          "upgradeType": null,
          "count": 9,
          "isUpgrade": false,
          "isChronoBoosted": false,
          "specialAction": null
        },
        "comment": ""
      }
    ],
    "raceMatchup": "ZvX",
    "url": "https://lotv.spawningtool.com/build/182643/"
  },
  {
    "title": "CalmHorizons - TvP 3Reaper 2Hellion",
    "steps": [
      {
        "supply": "12",
        "time": "0:00",
        "action": "SCV",
        "interpretedAction": {
          "unitType": 45,
          "upgradeType": null,
          "count": 1,
          "isUpgrade": false,
          "isChronoBoosted": false,
          "specialAction": null
        },
        "comment": ""
      },
      {
        "supply": "14",
        "time": "0:17",
        "action": "Supply Depot",
        "interpretedAction": {
          "unitType": 19,
          "upgradeType": null,
          "count": 1,
          "isUpgrade": false,
          "isChronoBoosted": false,
          "specialAction": null
        },
        "comment": ""
      },
      {
        "supply": "15",
        "time": "0:39",
        "action": "Barracks",
        "interpretedAction": {
          "unitType": 21,
          "upgradeType": null,
          "count": 1,
          "isUpgrade": false,
          "isChronoBoosted": false,
          "specialAction": null
        },
        "comment": ""
      },
      {
        "supply": "16",
        "time": "0:43",
        "action": "Refinery",
        "interpretedAction": {
          "unitType": 20,
          "upgradeType": null,
          "count": 1,
          "isUpgrade": false,
          "isChronoBoosted": false,
          "specialAction": null
        },
        "comment": ""
      },
      {
        "supply": "16",
        "time": "0:52",
        "action": "Refinery",
        "interpretedAction": {
          "unitType": 20,
          "upgradeType": null,
          "count": 1,
          "isUpgrade": false,
          "isChronoBoosted": false,
          "specialAction": null
        },
        "comment": ""
      },
      {
        "supply": "19",
        "time": "1:26",
        "action": "Reaper",
        "interpretedAction": {
          "unitType": 49,
          "upgradeType": null,
          "count": 1,
          "isUpgrade": false,
          "isChronoBoosted": false,
          "specialAction": null
        },
        "comment": ""
      },
      {
        "supply": "19",
        "time": "1:27",
        "action": "Orbital Command",
        "interpretedAction": {
          "unitType": 132,
          "upgradeType": null,
          "count": 1,
          "isUpgrade": false,
          "isChronoBoosted": false,
          "specialAction": null
        },
        "comment": ""
      },
      {
        "supply": "19",
        "time": "1:28",
        "action": "Supply Depot",
        "interpretedAction": {
          "unitType": 19,
          "upgradeType": null,
          "count": 1,
          "isUpgrade": false,
          "isChronoBoosted": false,
          "specialAction": null
        },
        "comment": ""
      },
      {
        "supply": "20",
        "time": "1:41",
        "action": "Factory",
        "interpretedAction": {
          "unitType": 27,
          "upgradeType": null,
          "count": 1,
          "isUpgrade": false,
          "isChronoBoosted": false,
          "specialAction": null
        },
        "comment": "Take 2+1 SCVs off gas"
      },
      {
        "supply": "23",
        "time": "2:20",
        "action": "Command Center",
        "interpretedAction": {
          "unitType": 18,
          "upgradeType": null,
          "count": 1,
          "isUpgrade": false,
          "isChronoBoosted": false,
          "specialAction": null
        },
        "comment": ""
      },
      {
        "supply": "24",
        "time": "2:25",
        "action": "Hellion",
        "interpretedAction": {
          "unitType": 53,
          "upgradeType": null,
          "count": 1,
          "isUpgrade": false,
          "isChronoBoosted": false,
          "specialAction": null
        },
        "comment": ""
      },
      {
        "supply": "26",
        "time": "2:32",
        "action": "Supply Depot",
        "interpretedAction": {
          "unitType": 19,
          "upgradeType": null,
          "count": 1,
          "isUpgrade": false,
          "isChronoBoosted": false,
          "specialAction": null
        },
        "comment": "Start putting 1+2 SCVs back on gas after 16/16 mineral saturation"
      },
      {
        "supply": "31",
        "time": "3:03",
        "action": "Starport",
        "interpretedAction": {
          "unitType": 28,
          "upgradeType": null,
          "count": 1,
          "isUpgrade": false,
          "isChronoBoosted": false,
          "specialAction": null
        },
        "comment": ""
      },
      {
        "supply": "32",
        "time": "3:10",
        "action": "Barracks Reactor",
        "interpretedAction": {
          "unitType": 38,
          "upgradeType": null,
          "count": 1,
          "isUpgrade": false,
          "isChronoBoosted": false,
          "specialAction": null
        },
        "comment": ""
      },
      {
        "supply": "32",
        "time": "3:08",
        "action": "Factory Tech Lab",
        "interpretedAction": {
          "unitType": 39,
          "upgradeType": null,
          "count": 1,
          "isUpgrade": false,
          "isChronoBoosted": false,
          "specialAction": null
        },
        "comment": ""
      },
      {
        "supply": "34",
        "time": "3:33",
        "action": "Orbital Command",
        "interpretedAction": {
          "unitType": 132,
          "upgradeType": null,
          "count": 1,
          "isUpgrade": false,
          "isChronoBoosted": false,
          "specialAction": null
        },
        "comment": ""
      },
      {
        "supply": "34",
        "time": "3:38",
        "action": "Barracks x2",
        "interpretedAction": {
          "unitType": 21,
          "upgradeType": null,
          "count": 2,
          "isUpgrade": false,
          "isChronoBoosted": false,
          "specialAction": null
        },
        "comment": ""
      },
      {
        "supply": "34",
        "time": "3:41",
        "action": "Siege Tank",
        "interpretedAction": {
          "unitType": 33,
          "upgradeType": null,
          "count": 1,
          "isUpgrade": false,
          "isChronoBoosted": false,
          "specialAction": null
        },
        "comment": ""
      },
      {
        "supply": "36",
        "time": "4:00",
        "action": "Marine x2",
        "interpretedAction": {
          "unitType": 48,
          "upgradeType": null,
          "count": 2,
          "isUpgrade": false,
          "isChronoBoosted": false,
          "specialAction": null
        },
        "comment": ""
      },
      {
        "supply": "39",
        "time": "4:02",
        "action": "Liberator",
        "interpretedAction": {
          "unitType": 689,
          "upgradeType": null,
          "count": 1,
          "isUpgrade": false,
          "isChronoBoosted": false,
          "specialAction": null
        },
        "comment": ""
      },
      {
        "supply": "39",
        "time": "4:09",
        "action": "Supply Depot",
        "interpretedAction": {
          "unitType": 19,
          "upgradeType": null,
          "count": 1,
          "isUpgrade": false,
          "isChronoBoosted": false,
          "specialAction": null
        },
        "comment": ""
      },
      {
        "supply": "47",
        "time": "4:28",
        "action": "Barracks Tech Lab x2",
        "interpretedAction": {
          "unitType": 37,
          "upgradeType": null,
          "count": 2,
          "isUpgrade": false,
          "isChronoBoosted": false,
          "specialAction": null
        },
        "comment": ""
      },
      {
        "supply": "49",
        "time": "4:31",
        "action": "Refinery",
        "interpretedAction": {
          "unitType": 20,
          "upgradeType": null,
          "count": 1,
          "isUpgrade": false,
          "isChronoBoosted": false,
          "specialAction": null
        },
        "comment": ""
      },
      {
        "supply": "49",
        "time": "4:35",
        "action": "Engineering Bay",
        "interpretedAction": {
          "unitType": 22,
          "upgradeType": null,
          "count": 1,
          "isUpgrade": false,
          "isChronoBoosted": false,
          "specialAction": null
        },
        "comment": ""
      },
      {
        "supply": "53",
        "time": "4:46",
        "action": "Stimpack",
        "interpretedAction": {
          "unitType": null,
          "upgradeType": null,
          "count": 1,
          "isUpgrade": false,
          "isChronoBoosted": false,
          "specialAction": null
        },
        "comment": ""
      },
      {
        "supply": "54",
        "time": "4:55",
        "action": "Combat Shield",
        "interpretedAction": {
          "unitType": null,
          "upgradeType": null,
          "count": 1,
          "isUpgrade": false,
          "isChronoBoosted": false,
          "specialAction": null
        },
        "comment": ""
      },
      {
        "supply": "57",
        "time": "5:02",
        "action": "Starport Reactor",
        "interpretedAction": {
          "unitType": 42,
          "upgradeType": null,
          "count": 1,
          "isUpgrade": false,
          "isChronoBoosted": false,
          "specialAction": null
        },
        "comment": ""
      },
      {
        "supply": "60",
        "time": "5:14",
        "action": "Refinery",
        "interpretedAction": {
          "unitType": 20,
          "upgradeType": null,
          "count": 1,
          "isUpgrade": false,
          "isChronoBoosted": false,
          "specialAction": null
        },
        "comment": ""
      },
      {
        "supply": "59",
        "time": "5:13",
        "action": "Supply Depot",
        "interpretedAction": {
          "unitType": 19,
          "upgradeType": null,
          "count": 1,
          "isUpgrade": false,
          "isChronoBoosted": false,
          "specialAction": null
        },
        "comment": ""
      },
      {
        "supply": "62",
        "time": "5:27",
        "action": "Terran Infantry Weapons Level 1",
        "interpretedAction": {
          "unitType": null,
          "upgradeType": null,
          "count": 1,
          "isUpgrade": false,
          "isChronoBoosted": false,
          "specialAction": null
        },
        "comment": ""
      },
      {
        "supply": "62",
        "time": "5:35",
        "action": "Marauder x2",
        "interpretedAction": {
          "unitType": 51,
          "upgradeType": null,
          "count": 2,
          "isUpgrade": false,
          "isChronoBoosted": false,
          "specialAction": null
        },
        "comment": ""
      },
      {
        "supply": "67",
        "time": "5:41",
        "action": "Medivac",
        "interpretedAction": {
          "unitType": 54,
          "upgradeType": null,
          "count": 1,
          "isUpgrade": false,
          "isChronoBoosted": false,
          "specialAction": null
        },
        "comment": ""
      },
      {
        "supply": "78",
        "time": "5:58",
        "action": "Medivac",
        "interpretedAction": {
          "unitType": 54,
          "upgradeType": null,
          "count": 1,
          "isUpgrade": false,
          "isChronoBoosted": false,
          "specialAction": null
        },
        "comment": ""
      },
      {
        "supply": "92",
        "time": "6:26",
        "action": "Concussive Shells",
        "interpretedAction": {
          "unitType": null,
          "upgradeType": null,
          "count": 1,
          "isUpgrade": false,
          "isChronoBoosted": false,
          "specialAction": null
        },
        "comment": ""
      },
      {
        "supply": "92",
        "time": "6:30",
        "action": "Marauder",
        "interpretedAction": {
          "unitType": 51,
          "upgradeType": null,
          "count": 1,
          "isUpgrade": false,
          "isChronoBoosted": false,
          "specialAction": null
        },
        "comment": ""
      },
      {
        "supply": "107",
        "time": "6:55",
        "action": "Command Center",
        "interpretedAction": {
          "unitType": 18,
          "upgradeType": null,
          "count": 1,
          "isUpgrade": false,
          "isChronoBoosted": false,
          "specialAction": null
        },
        "comment": ""
      },
      {
        "supply": "117",
        "time": "7:51",
        "action": "Barracks x2",
        "interpretedAction": {
          "unitType": 21,
          "upgradeType": null,
          "count": 2,
          "isUpgrade": false,
          "isChronoBoosted": false,
          "specialAction": null
        },
        "comment": ""
      }
    ],
    "raceMatchup": "TvP",
    "url": "https://lotv.spawningtool.com/build/182576/"
  },
  {
    "title": "Harstem 3-gate blink guide",
    "steps": [
      {
        "supply": "12",
        "time": "0:00",
        "action": "Probe",
        "interpretedAction": {
          "unitType": 84,
          "upgradeType": null,
          "count": 1,
          "isUpgrade": false,
          "isChronoBoosted": false,
          "specialAction": null
        },
        "comment": ""
      },
      {
        "supply": "13",
        "time": "0:12",
        "action": "Probe",
        "interpretedAction": {
          "unitType": 84,
          "upgradeType": null,
          "count": 1,
          "isUpgrade": false,
          "isChronoBoosted": false,
          "specialAction": null
        },
        "comment": ""
      },
      {
        "supply": "14",
        "time": "0:17",
        "action": "Pylon",
        "interpretedAction": {
          "unitType": 60,
          "upgradeType": null,
          "count": 1,
          "isUpgrade": false,
          "isChronoBoosted": false,
          "specialAction": null
        },
        "comment": ""
      },
      {
        "supply": "14",
        "time": "0:24",
        "action": "Probe",
        "interpretedAction": {
          "unitType": 84,
          "upgradeType": null,
          "count": 1,
          "isUpgrade": false,
          "isChronoBoosted": false,
          "specialAction": null
        },
        "comment": ""
      },
      {
        "supply": "15",
        "time": "0:35",
        "action": "Gateway",
        "interpretedAction": {
          "unitType": 62,
          "upgradeType": null,
          "count": 1,
          "isUpgrade": false,
          "isChronoBoosted": false,
          "specialAction": null
        },
        "comment": ""
      },
      {
        "supply": "15",
        "time": "0:37",
        "action": "Probe (Chrono Boost)",
        "interpretedAction": {
          "unitType": 84,
          "upgradeType": null,
          "count": 1,
          "isUpgrade": false,
          "isChronoBoosted": true,
          "specialAction": null
        },
        "comment": ""
      },
      {
        "supply": "16",
        "time": "0:47",
        "action": "Assimilator, Probe x2 (Chrono Boost)",
        "interpretedAction": {
          "unitType": 61,
          "upgradeType": null,
          "count": 2,
          "isUpgrade": false,
          "isChronoBoosted": true,
          "specialAction": null
        },
        "comment": ""
      },
      {
        "supply": "16",
        "time": "0:47",
        "action": "Assimilator, Probe x2 (Chrono Boost)",
        "interpretedAction": {
          "unitType": 84,
          "upgradeType": null,
          "count": 2,
          "isUpgrade": false,
          "isChronoBoosted": true,
          "specialAction": null
        },
        "comment": ""
      },
      {
        "supply": "18",
        "time": "1:04",
        "action": "Probe",
        "interpretedAction": {
          "unitType": 84,
          "upgradeType": null,
          "count": 1,
          "isUpgrade": false,
          "isChronoBoosted": false,
          "specialAction": null
        },
        "comment": ""
      },
      {
        "supply": "19",
        "time": "1:16",
        "action": "Probe",
        "interpretedAction": {
          "unitType": 84,
          "upgradeType": null,
          "count": 1,
          "isUpgrade": false,
          "isChronoBoosted": false,
          "specialAction": null
        },
        "comment": ""
      },
      {
        "supply": "20",
        "time": "1:24",
        "action": "Cybernetics Core",
        "interpretedAction": {
          "unitType": 72,
          "upgradeType": null,
          "count": 1,
          "isUpgrade": false,
          "isChronoBoosted": false,
          "specialAction": null
        },
        "comment": ""
      },
      {
        "supply": "20",
        "time": "1:32",
        "action": "Nexus",
        "interpretedAction": {
          "unitType": 59,
          "upgradeType": null,
          "count": 1,
          "isUpgrade": false,
          "isChronoBoosted": false,
          "specialAction": null
        },
        "comment": ""
      },
      {
        "supply": "20",
        "time": "1:36",
        "action": "Probe",
        "interpretedAction": {
          "unitType": 84,
          "upgradeType": null,
          "count": 1,
          "isUpgrade": false,
          "isChronoBoosted": false,
          "specialAction": null
        },
        "comment": ""
      },
      {
        "supply": "21",
        "time": "1:43",
        "action": "Pylon",
        "interpretedAction": {
          "unitType": 60,
          "upgradeType": null,
          "count": 1,
          "isUpgrade": false,
          "isChronoBoosted": false,
          "specialAction": null
        },
        "comment": ""
      },
      {
        "supply": "21",
        "time": "1:48",
        "action": "Probe",
        "interpretedAction": {
          "unitType": 84,
          "upgradeType": null,
          "count": 1,
          "isUpgrade": false,
          "isChronoBoosted": false,
          "specialAction": null
        },
        "comment": ""
      },
      {
        "supply": "21",
        "time": "1:52",
        "action": "Assimilator",
        "interpretedAction": {
          "unitType": 61,
          "upgradeType": null,
          "count": 1,
          "isUpgrade": false,
          "isChronoBoosted": false,
          "specialAction": null
        },
        "comment": ""
      },
      {
        "supply": "22",
        "time": "1:58",
        "action": "Adept (Chrono Boost)",
        "interpretedAction": {
          "unitType": 311,
          "upgradeType": null,
          "count": 1,
          "isUpgrade": false,
          "isChronoBoosted": true,
          "specialAction": null
        },
        "comment": ""
      },
      {
        "supply": "25",
        "time": "2:04",
        "action": "Warp Gate",
        "interpretedAction": {
          "unitType": 133,
          "upgradeType": null,
          "count": 1,
          "isUpgrade": false,
          "isChronoBoosted": false,
          "specialAction": null
        },
        "comment": ""
      },
      {
        "supply": "26",
        "time": "2:19",
        "action": "Adept (Chrono Boost)",
        "interpretedAction": {
          "unitType": 311,
          "upgradeType": null,
          "count": 1,
          "isUpgrade": false,
          "isChronoBoosted": true,
          "specialAction": null
        },
        "comment": "Position these 2 adepts in the middle of the map to scout for 3-rax or other moveouts"
      },
      {
        "supply": "29",
        "time": "2:34",
        "action": "Twilight Council",
        "interpretedAction": {
          "unitType": 65,
          "upgradeType": null,
          "count": 1,
          "isUpgrade": false,
          "isChronoBoosted": false,
          "specialAction": null
        },
        "comment": ""
      },
      {
        "supply": "30",
        "time": "2:44",
        "action": "Gateway",
        "interpretedAction": {
          "unitType": 62,
          "upgradeType": null,
          "count": 1,
          "isUpgrade": false,
          "isChronoBoosted": false,
          "specialAction": null
        },
        "comment": ""
      },
      {
        "supply": "33",
        "time": "3:02",
        "action": "Blink (Chrono Boost)",
        "interpretedAction": {
          "unitType": null,
          "upgradeType": 87,
          "count": 1,
          "isUpgrade": true,
          "isChronoBoosted": true,
          "specialAction": null
        },
        "comment": ""
      },
      {
        "supply": "35",
        "time": "3:15",
        "action": "Robotics Facility",
        "interpretedAction": {
          "unitType": 71,
          "upgradeType": null,
          "count": 1,
          "isUpgrade": false,
          "isChronoBoosted": false,
          "specialAction": null
        },
        "comment": ""
      },
      {
        "supply": "35",
        "time": "3:19",
        "action": "Gateway",
        "interpretedAction": {
          "unitType": 62,
          "upgradeType": null,
          "count": 1,
          "isUpgrade": false,
          "isChronoBoosted": false,
          "specialAction": null
        },
        "comment": ""
      },
      {
        "supply": "38",
        "time": "3:30",
        "action": "Pylon",
        "interpretedAction": {
          "unitType": 60,
          "upgradeType": null,
          "count": 1,
          "isUpgrade": false,
          "isChronoBoosted": false,
          "specialAction": null
        },
        "comment": ""
      },
      {
        "supply": "40",
        "time": "3:46",
        "action": "Pylon",
        "interpretedAction": {
          "unitType": 60,
          "upgradeType": null,
          "count": 1,
          "isUpgrade": false,
          "isChronoBoosted": false,
          "specialAction": null
        },
        "comment": ""
      },
      {
        "supply": "41",
        "time": "3:52",
        "action": "Stalker x2",
        "interpretedAction": {
          "unitType": 74,
          "upgradeType": null,
          "count": 2,
          "isUpgrade": false,
          "isChronoBoosted": false,
          "specialAction": null
        },
        "comment": ""
      },
      {
        "supply": "46",
        "time": "4:00",
        "action": "Pylon, Warp Prism (Chrono Boost)",
        "interpretedAction": {
          "unitType": 60,
          "upgradeType": null,
          "count": 1,
          "isUpgrade": false,
          "isChronoBoosted": true,
          "specialAction": null
        },
        "comment": ""
      },
      {
        "supply": "46",
        "time": "4:00",
        "action": "Pylon, Warp Prism (Chrono Boost)",
        "interpretedAction": {
          "unitType": 81,
          "upgradeType": null,
          "count": 1,
          "isUpgrade": false,
          "isChronoBoosted": true,
          "specialAction": null
        },
        "comment": ""
      },
      {
        "supply": "48",
        "time": "4:15",
        "action": "Stalker x3",
        "interpretedAction": {
          "unitType": 74,
          "upgradeType": null,
          "count": 3,
          "isUpgrade": false,
          "isChronoBoosted": false,
          "specialAction": null
        },
        "comment": ""
      },
      {
        "supply": "54",
        "time": "4:38",
        "action": "Stalker x3",
        "interpretedAction": {
          "unitType": 74,
          "upgradeType": null,
          "count": 3,
          "isUpgrade": false,
          "isChronoBoosted": false,
          "specialAction": null
        },
        "comment": ""
      },
      {
        "supply": "60",
        "time": "4:49",
        "action": "Nexus",
        "interpretedAction": {
          "unitType": 59,
          "upgradeType": null,
          "count": 1,
          "isUpgrade": false,
          "isChronoBoosted": false,
          "specialAction": null
        },
        "comment": "Prioritize getting stalkers 8-11 over this nexus"
      },
      {
        "supply": "62",
        "time": "5:01",
        "action": "Assimilator",
        "interpretedAction": {
          "unitType": 61,
          "upgradeType": null,
          "count": 1,
          "isUpgrade": false,
          "isChronoBoosted": false,
          "specialAction": null
        },
        "comment": ""
      },
      {
        "supply": "62",
        "time": "5:02",
        "action": "Stalker x2",
        "interpretedAction": {
          "unitType": 74,
          "upgradeType": null,
          "count": 2,
          "isUpgrade": false,
          "isChronoBoosted": false,
          "specialAction": null
        },
        "comment": "Blink into the main as soon as this 11th stalker finishes. Resume probing"
      },
      {
        "supply": "78",
        "time": "5:32",
        "action": "Forge",
        "interpretedAction": {
          "unitType": 63,
          "upgradeType": null,
          "count": 1,
          "isUpgrade": false,
          "isChronoBoosted": false,
          "specialAction": null
        },
        "comment": ""
      },
      {
        "supply": "79",
        "time": "5:39",
        "action": "Gateway",
        "interpretedAction": {
          "unitType": 62,
          "upgradeType": null,
          "count": 1,
          "isUpgrade": false,
          "isChronoBoosted": false,
          "specialAction": null
        },
        "comment": ""
      },
      {
        "supply": "69",
        "time": "5:15",
        "action": "Action",
        "interpretedAction": {
          "unitType": null,
          "upgradeType": null,
          "count": 1,
          "isUpgrade": false,
          "isChronoBoosted": false,
          "specialAction": null
        },
        "comment": "Blink into the main"
      }
    ],
    "raceMatchup": "PvT",
    "url": "https://lotv.spawningtool.com/build/180543/"
  },
  {
    "title": "5 Minute Drill",
    "steps": [
      {
        "supply": "12",
        "time": "0:00",
        "action": "Drone",
        "interpretedAction": {
          "unitType": 104,
          "upgradeType": null,
          "count": 1,
          "isUpgrade": false,
          "isChronoBoosted": false,
          "specialAction": null
        },
        "comment": ""
      },
      {
        "supply": "13",
        "time": "0:12",
        "action": "Overlord",
        "interpretedAction": {
          "unitType": 106,
          "upgradeType": null,
          "count": 1,
          "isUpgrade": false,
          "isChronoBoosted": false,
          "specialAction": null
        },
        "comment": ""
      },
      {
        "supply": "13",
        "time": "0:16",
        "action": "Drone",
        "interpretedAction": {
          "unitType": 104,
          "upgradeType": null,
          "count": 1,
          "isUpgrade": false,
          "isChronoBoosted": false,
          "specialAction": null
        },
        "comment": ""
      },
      {
        "supply": "14",
        "time": "0:30",
        "action": "Drone x3",
        "interpretedAction": {
          "unitType": 104,
          "upgradeType": null,
          "count": 3,
          "isUpgrade": false,
          "isChronoBoosted": false,
          "specialAction": null
        },
        "comment": ""
      },
      {
        "supply": "17",
        "time": "0:51",
        "action": "Hatchery",
        "interpretedAction": {
          "unitType": 86,
          "upgradeType": null,
          "count": 1,
          "isUpgrade": false,
          "isChronoBoosted": false,
          "specialAction": null
        },
        "comment": ""
      },
      {
        "supply": "17",
        "time": "0:54",
        "action": "Drone x2",
        "interpretedAction": {
          "unitType": 104,
          "upgradeType": null,
          "count": 2,
          "isUpgrade": false,
          "isChronoBoosted": false,
          "specialAction": null
        },
        "comment": ""
      },
      {
        "supply": "18",
        "time": "1:09",
        "action": "Extractor",
        "interpretedAction": {
          "unitType": 88,
          "upgradeType": null,
          "count": 1,
          "isUpgrade": false,
          "isChronoBoosted": false,
          "specialAction": null
        },
        "comment": ""
      },
      {
        "supply": "17",
        "time": "1:13",
        "action": "Spawning Pool",
        "interpretedAction": {
          "unitType": 89,
          "upgradeType": null,
          "count": 1,
          "isUpgrade": false,
          "isChronoBoosted": false,
          "specialAction": null
        },
        "comment": ""
      },
      {
        "supply": "17",
        "time": "1:15",
        "action": "Drone x2",
        "interpretedAction": {
          "unitType": 104,
          "upgradeType": null,
          "count": 2,
          "isUpgrade": false,
          "isChronoBoosted": false,
          "specialAction": null
        },
        "comment": ""
      },
      {
        "supply": "18",
        "time": "1:28",
        "action": "Drone",
        "interpretedAction": {
          "unitType": 104,
          "upgradeType": null,
          "count": 1,
          "isUpgrade": false,
          "isChronoBoosted": false,
          "specialAction": null
        },
        "comment": "Pull 2 drones off gas when youre at 56 gas and send them to mine and natural."
      },
      {
        "supply": "21",
        "time": "2:01",
        "action": "Zergling x4",
        "interpretedAction": {
          "unitType": 105,
          "upgradeType": null,
          "count": 4,
          "isUpgrade": false,
          "isChronoBoosted": false,
          "specialAction": null
        },
        "comment": ""
      },
      {
        "supply": "21",
        "time": "2:02",
        "action": "Queen x2",
        "interpretedAction": {
          "unitType": 126,
          "upgradeType": null,
          "count": 2,
          "isUpgrade": false,
          "isChronoBoosted": false,
          "specialAction": null
        },
        "comment": ""
      },
      {
        "supply": "27",
        "time": "2:13",
        "action": "Hatchery",
        "interpretedAction": {
          "unitType": 86,
          "upgradeType": null,
          "count": 1,
          "isUpgrade": false,
          "isChronoBoosted": false,
          "specialAction": null
        },
        "comment": ""
      },
      {
        "supply": "26",
        "time": "2:18",
        "action": "Overlord",
        "interpretedAction": {
          "unitType": 106,
          "upgradeType": null,
          "count": 1,
          "isUpgrade": false,
          "isChronoBoosted": false,
          "specialAction": null
        },
        "comment": ""
      },
      {
        "supply": "28",
        "time": "2:36",
        "action": "Metabolic Boost",
        "interpretedAction": {
          "unitType": null,
          "upgradeType": null,
          "count": 1,
          "isUpgrade": false,
          "isChronoBoosted": false,
          "specialAction": null
        },
        "comment": ""
      },
      {
        "supply": "31",
        "time": "2:44",
        "action": "Queen",
        "interpretedAction": {
          "unitType": 126,
          "upgradeType": null,
          "count": 1,
          "isUpgrade": false,
          "isChronoBoosted": false,
          "specialAction": null
        },
        "comment": ""
      },
      {
        "supply": "31",
        "time": "2:49",
        "action": "Overlord",
        "interpretedAction": {
          "unitType": 106,
          "upgradeType": null,
          "count": 1,
          "isUpgrade": false,
          "isChronoBoosted": false,
          "specialAction": null
        },
        "comment": ""
      },
      {
        "supply": "36",
        "time": "3:04",
        "action": "Overlord",
        "interpretedAction": {
          "unitType": 106,
          "upgradeType": null,
          "count": 1,
          "isUpgrade": false,
          "isChronoBoosted": false,
          "specialAction": null
        },
        "comment": ""
      },
      {
        "supply": "40",
        "time": "3:20",
        "action": "Overlord",
        "interpretedAction": {
          "unitType": 106,
          "upgradeType": null,
          "count": 1,
          "isUpgrade": false,
          "isChronoBoosted": false,
          "specialAction": null
        },
        "comment": ""
      },
      {
        "supply": "40",
        "time": "3:24",
        "action": "Queen",
        "interpretedAction": {
          "unitType": 126,
          "upgradeType": null,
          "count": 1,
          "isUpgrade": false,
          "isChronoBoosted": false,
          "specialAction": null
        },
        "comment": "2 drones back on gas at 3:30"
      },
      {
        "supply": "46",
        "time": "3:37",
        "action": "Queen",
        "interpretedAction": {
          "unitType": 126,
          "upgradeType": null,
          "count": 1,
          "isUpgrade": false,
          "isChronoBoosted": false,
          "specialAction": null
        },
        "comment": ""
      },
      {
        "supply": "46",
        "time": "3:40",
        "action": "Baneling Nest",
        "interpretedAction": {
          "unitType": 96,
          "upgradeType": null,
          "count": 1,
          "isUpgrade": false,
          "isChronoBoosted": false,
          "specialAction": null
        },
        "comment": ""
      },
      {
        "supply": "59",
        "time": "4:03",
        "action": "Queen",
        "interpretedAction": {
          "unitType": 126,
          "upgradeType": null,
          "count": 1,
          "isUpgrade": false,
          "isChronoBoosted": false,
          "specialAction": null
        },
        "comment": ""
      },
      {
        "supply": "65",
        "time": "4:30",
        "action": "Evolution Chamber x2",
        "interpretedAction": {
          "unitType": 90,
          "upgradeType": null,
          "count": 2,
          "isUpgrade": false,
          "isChronoBoosted": false,
          "specialAction": null
        },
        "comment": ""
      },
      {
        "supply": "66",
        "time": "4:32",
        "action": "Zergling x10",
        "interpretedAction": {
          "unitType": 105,
          "upgradeType": null,
          "count": 10,
          "isUpgrade": false,
          "isChronoBoosted": false,
          "specialAction": null
        },
        "comment": ""
      },
      {
        "supply": "70",
        "time": "4:39",
        "action": "Zergling x6",
        "interpretedAction": {
          "unitType": 105,
          "upgradeType": null,
          "count": 6,
          "isUpgrade": false,
          "isChronoBoosted": false,
          "specialAction": null
        },
        "comment": ""
      }
    ],
    "raceMatchup": "ZvT",
    "url": "https://lotv.spawningtool.com/build/180482/"
  },
  {
    "title": "6 Gate DT 4:30",
    "steps": [
      {
        "supply": "13",
        "time": "0:18",
        "action": "Pylon",
        "interpretedAction": {
          "unitType": 60,
          "upgradeType": null,
          "count": 1,
          "isUpgrade": false,
          "isChronoBoosted": false,
          "specialAction": null
        },
        "comment": ""
      },
      {
        "supply": "15",
        "time": "0:35",
        "action": "Gateway",
        "interpretedAction": {
          "unitType": 62,
          "upgradeType": null,
          "count": 1,
          "isUpgrade": false,
          "isChronoBoosted": false,
          "specialAction": null
        },
        "comment": ""
      },
      {
        "supply": "16",
        "time": "0:48",
        "action": "Assimilator",
        "interpretedAction": {
          "unitType": 61,
          "upgradeType": null,
          "count": 1,
          "isUpgrade": false,
          "isChronoBoosted": false,
          "specialAction": null
        },
        "comment": ""
      },
      {
        "supply": "19",
        "time": "1:25",
        "action": "Nexus",
        "interpretedAction": {
          "unitType": 59,
          "upgradeType": null,
          "count": 1,
          "isUpgrade": false,
          "isChronoBoosted": false,
          "specialAction": null
        },
        "comment": ""
      },
      {
        "supply": "19",
        "time": "1:40",
        "action": "Cybernetics Core",
        "interpretedAction": {
          "unitType": 72,
          "upgradeType": null,
          "count": 1,
          "isUpgrade": false,
          "isChronoBoosted": false,
          "specialAction": null
        },
        "comment": ""
      },
      {
        "supply": "19",
        "time": "1:45",
        "action": "Assimilator, Probe x2 (Chrono Boost)",
        "interpretedAction": {
          "unitType": 61,
          "upgradeType": null,
          "count": 2,
          "isUpgrade": false,
          "isChronoBoosted": true,
          "specialAction": null
        },
        "comment": ""
      },
      {
        "supply": "19",
        "time": "1:45",
        "action": "Assimilator, Probe x2 (Chrono Boost)",
        "interpretedAction": {
          "unitType": 84,
          "upgradeType": null,
          "count": 2,
          "isUpgrade": false,
          "isChronoBoosted": true,
          "specialAction": null
        },
        "comment": ""
      },
      {
        "supply": "21",
        "time": "1:52",
        "action": "Pylon",
        "interpretedAction": {
          "unitType": 60,
          "upgradeType": null,
          "count": 1,
          "isUpgrade": false,
          "isChronoBoosted": false,
          "specialAction": null
        },
        "comment": ""
      },
      {
        "supply": "22",
        "time": "2:15",
        "action": "Twilight Council",
        "interpretedAction": {
          "unitType": 65,
          "upgradeType": null,
          "count": 1,
          "isUpgrade": false,
          "isChronoBoosted": false,
          "specialAction": null
        },
        "comment": ""
      },
      {
        "supply": "23",
        "time": "2:20",
        "action": "Warp Gate",
        "interpretedAction": {
          "unitType": 133,
          "upgradeType": null,
          "count": 1,
          "isUpgrade": false,
          "isChronoBoosted": false,
          "specialAction": null
        },
        "comment": ""
      },
      {
        "supply": "28",
        "time": "2:30",
        "action": "Robotics Bay",
        "interpretedAction": {
          "unitType": 70,
          "upgradeType": null,
          "count": 1,
          "isUpgrade": false,
          "isChronoBoosted": false,
          "specialAction": null
        },
        "comment": ""
      },
      {
        "supply": "34",
        "time": "2:57",
        "action": "Dark Shrine",
        "interpretedAction": {
          "unitType": 69,
          "upgradeType": null,
          "count": 1,
          "isUpgrade": false,
          "isChronoBoosted": false,
          "specialAction": null
        },
        "comment": ""
      },
      {
        "supply": "38",
        "time": "3:15",
        "action": "Warp Prism (Chrono Boost)",
        "interpretedAction": {
          "unitType": 81,
          "upgradeType": null,
          "count": 1,
          "isUpgrade": false,
          "isChronoBoosted": true,
          "specialAction": null
        },
        "comment": ""
      },
      {
        "supply": "40",
        "time": "3:30",
        "action": "Gateway",
        "interpretedAction": {
          "unitType": 62,
          "upgradeType": null,
          "count": 1,
          "isUpgrade": false,
          "isChronoBoosted": false,
          "specialAction": null
        },
        "comment": ""
      },
      {
        "supply": "42",
        "time": "3:35",
        "action": "Gateway",
        "interpretedAction": {
          "unitType": 62,
          "upgradeType": null,
          "count": 1,
          "isUpgrade": false,
          "isChronoBoosted": false,
          "specialAction": null
        },
        "comment": ""
      },
      {
        "supply": "42",
        "time": "3:40",
        "action": "Gateway",
        "interpretedAction": {
          "unitType": 62,
          "upgradeType": null,
          "count": 1,
          "isUpgrade": false,
          "isChronoBoosted": false,
          "specialAction": null
        },
        "comment": ""
      },
      {
        "supply": "40",
        "time": "3:50",
        "action": "Assimilator",
        "interpretedAction": {
          "unitType": 61,
          "upgradeType": null,
          "count": 1,
          "isUpgrade": false,
          "isChronoBoosted": false,
          "specialAction": null
        },
        "comment": ""
      },
      {
        "supply": "43",
        "time": "3:53",
        "action": "Assimilator",
        "interpretedAction": {
          "unitType": 61,
          "upgradeType": null,
          "count": 1,
          "isUpgrade": false,
          "isChronoBoosted": false,
          "specialAction": null
        },
        "comment": ""
      },
      {
        "supply": "44",
        "time": "4:00",
        "action": "Pylon",
        "interpretedAction": {
          "unitType": 60,
          "upgradeType": null,
          "count": 1,
          "isUpgrade": false,
          "isChronoBoosted": false,
          "specialAction": null
        },
        "comment": ""
      },
      {
        "supply": "46",
        "time": "4:05",
        "action": "Gateway x2, Pylon",
        "interpretedAction": {
          "unitType": 62,
          "upgradeType": null,
          "count": 2,
          "isUpgrade": false,
          "isChronoBoosted": false,
          "specialAction": null
        },
        "comment": ""
      },
      {
        "supply": "46",
        "time": "4:05",
        "action": "Gateway x2, Pylon",
        "interpretedAction": {
          "unitType": 60,
          "upgradeType": null,
          "count": 2,
          "isUpgrade": false,
          "isChronoBoosted": false,
          "specialAction": null
        },
        "comment": ""
      },
      {
        "supply": "46",
        "time": "4:10",
        "action": "Gateway",
        "interpretedAction": {
          "unitType": 62,
          "upgradeType": null,
          "count": 1,
          "isUpgrade": false,
          "isChronoBoosted": false,
          "specialAction": null
        },
        "comment": ""
      },
      {
        "supply": "46",
        "time": "4:15",
        "action": "Pylon",
        "interpretedAction": {
          "unitType": 60,
          "upgradeType": null,
          "count": 1,
          "isUpgrade": false,
          "isChronoBoosted": false,
          "specialAction": null
        },
        "comment": ""
      }
    ],
    "raceMatchup": "PvX",
    "url": "https://lotv.spawningtool.com/build/180478/"
  },
  {
    "title": "Opening P Antho",
    "steps": [
      {
        "supply": "13",
        "time": "",
        "action": "Pylon",
        "interpretedAction": {
          "unitType": 60,
          "upgradeType": null,
          "count": 1,
          "isUpgrade": false,
          "isChronoBoosted": false,
          "specialAction": null
        },
        "comment": ""
      },
      {
        "supply": "16",
        "time": "",
        "action": "Gateway",
        "interpretedAction": {
          "unitType": 62,
          "upgradeType": null,
          "count": 1,
          "isUpgrade": false,
          "isChronoBoosted": false,
          "specialAction": null
        },
        "comment": ""
      },
      {
        "supply": "17",
        "time": "",
        "action": "Assimilator",
        "interpretedAction": {
          "unitType": 61,
          "upgradeType": null,
          "count": 1,
          "isUpgrade": false,
          "isChronoBoosted": false,
          "specialAction": null
        },
        "comment": ""
      },
      {
        "supply": "20",
        "time": "",
        "action": "Cybernetics Core",
        "interpretedAction": {
          "unitType": 72,
          "upgradeType": null,
          "count": 1,
          "isUpgrade": false,
          "isChronoBoosted": false,
          "specialAction": null
        },
        "comment": ""
      },
      {
        "supply": "20",
        "time": "",
        "action": "Nexus",
        "interpretedAction": {
          "unitType": 59,
          "upgradeType": null,
          "count": 1,
          "isUpgrade": false,
          "isChronoBoosted": false,
          "specialAction": null
        },
        "comment": ""
      },
      {
        "supply": "21",
        "time": "",
        "action": "Assimilator",
        "interpretedAction": {
          "unitType": 61,
          "upgradeType": null,
          "count": 1,
          "isUpgrade": false,
          "isChronoBoosted": false,
          "specialAction": null
        },
        "comment": ""
      },
      {
        "supply": "22",
        "time": "",
        "action": "Pylon",
        "interpretedAction": {
          "unitType": 60,
          "upgradeType": null,
          "count": 1,
          "isUpgrade": false,
          "isChronoBoosted": false,
          "specialAction": null
        },
        "comment": ""
      },
      {
        "supply": "28",
        "time": "",
        "action": "Twilight Council",
        "interpretedAction": {
          "unitType": 65,
          "upgradeType": null,
          "count": 1,
          "isUpgrade": false,
          "isChronoBoosted": false,
          "specialAction": null
        },
        "comment": ""
      },
      {
        "supply": "30",
        "time": "",
        "action": "Gateway",
        "interpretedAction": {
          "unitType": 62,
          "upgradeType": null,
          "count": 1,
          "isUpgrade": false,
          "isChronoBoosted": false,
          "specialAction": null
        },
        "comment": ""
      },
      {
        "supply": "30",
        "time": "",
        "action": "Robotics Bay",
        "interpretedAction": {
          "unitType": 70,
          "upgradeType": null,
          "count": 1,
          "isUpgrade": false,
          "isChronoBoosted": false,
          "specialAction": null
        },
        "comment": ""
      },
      {
        "supply": "31",
        "time": "",
        "action": "Gateway x3",
        "interpretedAction": {
          "unitType": 62,
          "upgradeType": null,
          "count": 3,
          "isUpgrade": false,
          "isChronoBoosted": false,
          "specialAction": null
        },
        "comment": ""
      }
    ],
    "raceMatchup": "PvX",
    "url": "https://lotv.spawningtool.com/build/180497/"
  },
  {
    "title": "Beginner Terran Build Order HuShang Tutorials",
    "steps": [
      {
        "supply": "12",
        "time": "0:00",
        "action": "SCV",
        "interpretedAction": {
          "unitType": 45,
          "upgradeType": null,
          "count": 1,
          "isUpgrade": false,
          "isChronoBoosted": false,
          "specialAction": null
        },
        "comment": ""
      },
      {
        "supply": "13",
        "time": "0:12",
        "action": "SCV",
        "interpretedAction": {
          "unitType": 45,
          "upgradeType": null,
          "count": 1,
          "isUpgrade": false,
          "isChronoBoosted": false,
          "specialAction": null
        },
        "comment": ""
      },
      {
        "supply": "14",
        "time": "0:17",
        "action": "Supply Depot",
        "interpretedAction": {
          "unitType": 19,
          "upgradeType": null,
          "count": 1,
          "isUpgrade": false,
          "isChronoBoosted": false,
          "specialAction": null
        },
        "comment": ""
      },
      {
        "supply": "14",
        "time": "0:24",
        "action": "SCV",
        "interpretedAction": {
          "unitType": 45,
          "upgradeType": null,
          "count": 1,
          "isUpgrade": false,
          "isChronoBoosted": false,
          "specialAction": null
        },
        "comment": ""
      },
      {
        "supply": "15",
        "time": "0:39",
        "action": "SCV",
        "interpretedAction": {
          "unitType": 45,
          "upgradeType": null,
          "count": 1,
          "isUpgrade": false,
          "isChronoBoosted": false,
          "specialAction": null
        },
        "comment": ""
      },
      {
        "supply": "15",
        "time": "0:40",
        "action": "Barracks",
        "interpretedAction": {
          "unitType": 21,
          "upgradeType": null,
          "count": 1,
          "isUpgrade": false,
          "isChronoBoosted": false,
          "specialAction": null
        },
        "comment": ""
      },
      {
        "supply": "16",
        "time": "0:45",
        "action": "Refinery",
        "interpretedAction": {
          "unitType": 20,
          "upgradeType": null,
          "count": 1,
          "isUpgrade": false,
          "isChronoBoosted": false,
          "specialAction": null
        },
        "comment": ""
      },
      {
        "supply": "16",
        "time": "0:51",
        "action": "SCV",
        "interpretedAction": {
          "unitType": 45,
          "upgradeType": null,
          "count": 1,
          "isUpgrade": false,
          "isChronoBoosted": false,
          "specialAction": null
        },
        "comment": ""
      },
      {
        "supply": "17",
        "time": "1:03",
        "action": "SCV",
        "interpretedAction": {
          "unitType": 45,
          "upgradeType": null,
          "count": 1,
          "isUpgrade": false,
          "isChronoBoosted": false,
          "specialAction": null
        },
        "comment": ""
      },
      {
        "supply": "17",
        "time": "1:05",
        "action": "Spec Ops Ghost",
        "interpretedAction": {
          "unitType": 45,
          "upgradeType": null,
          "count": 1,
          "isUpgrade": false,
          "isChronoBoosted": false,
          "specialAction": "Scouting with SCV"
        },
        "comment": "SCOUT CSV"
      },
      {
        "supply": "18",
        "time": "1:15",
        "action": "SCV",
        "interpretedAction": {
          "unitType": 45,
          "upgradeType": null,
          "count": 1,
          "isUpgrade": false,
          "isChronoBoosted": false,
          "specialAction": null
        },
        "comment": ""
      },
      {
        "supply": "19",
        "time": "1:30",
        "action": "Marine, Orbital Command",
        "interpretedAction": {
          "unitType": 48,
          "upgradeType": null,
          "count": 1,
          "isUpgrade": false,
          "isChronoBoosted": false,
          "specialAction": null
        },
        "comment": ""
      },
      {
        "supply": "19",
        "time": "1:30",
        "action": "Marine, Orbital Command",
        "interpretedAction": {
          "unitType": 132,
          "upgradeType": null,
          "count": 1,
          "isUpgrade": false,
          "isChronoBoosted": false,
          "specialAction": null
        },
        "comment": ""
      },
      {
        "supply": "20",
        "time": "1:41",
        "action": "Command Center",
        "interpretedAction": {
          "unitType": 18,
          "upgradeType": null,
          "count": 1,
          "isUpgrade": false,
          "isChronoBoosted": false,
          "specialAction": null
        },
        "comment": ""
      },
      {
        "supply": "20",
        "time": "1:49",
        "action": "Barracks Reactor",
        "interpretedAction": {
          "unitType": 38,
          "upgradeType": null,
          "count": 1,
          "isUpgrade": false,
          "isChronoBoosted": false,
          "specialAction": null
        },
        "comment": ""
      },
      {
        "supply": "20",
        "time": "1:55",
        "action": "Supply Depot",
        "interpretedAction": {
          "unitType": 19,
          "upgradeType": null,
          "count": 1,
          "isUpgrade": false,
          "isChronoBoosted": false,
          "specialAction": null
        },
        "comment": ""
      },
      {
        "supply": "20",
        "time": "1:56",
        "action": "SCV",
        "interpretedAction": {
          "unitType": 45,
          "upgradeType": null,
          "count": 1,
          "isUpgrade": false,
          "isChronoBoosted": false,
          "specialAction": null
        },
        "comment": ""
      },
      {
        "supply": "21",
        "time": "2:00",
        "action": "Crystalline Amplifiers",
        "interpretedAction": {
          "unitType": null,
          "upgradeType": null,
          "count": 1,
          "isUpgrade": false,
          "isChronoBoosted": false,
          "specialAction": null
        },
        "comment": "CALL DOWN MULES!!!"
      },
      {
        "supply": "21",
        "time": "2:09",
        "action": "SCV",
        "interpretedAction": {
          "unitType": 45,
          "upgradeType": null,
          "count": 1,
          "isUpgrade": false,
          "isChronoBoosted": false,
          "specialAction": null
        },
        "comment": ""
      },
      {
        "supply": "21",
        "time": "2:12",
        "action": "Factory",
        "interpretedAction": {
          "unitType": 27,
          "upgradeType": null,
          "count": 1,
          "isUpgrade": false,
          "isChronoBoosted": false,
          "specialAction": null
        },
        "comment": ""
      },
      {
        "supply": "22",
        "time": "2:21",
        "action": "SCV",
        "interpretedAction": {
          "unitType": 45,
          "upgradeType": null,
          "count": 1,
          "isUpgrade": false,
          "isChronoBoosted": false,
          "specialAction": null
        },
        "comment": ""
      },
      {
        "supply": "23",
        "time": "2:23",
        "action": "Bunker",
        "interpretedAction": {
          "unitType": 24,
          "upgradeType": null,
          "count": 1,
          "isUpgrade": false,
          "isChronoBoosted": false,
          "specialAction": null
        },
        "comment": ""
      },
      {
        "supply": "23",
        "time": "2:25",
        "action": "Marine x2",
        "interpretedAction": {
          "unitType": 48,
          "upgradeType": null,
          "count": 2,
          "isUpgrade": false,
          "isChronoBoosted": false,
          "specialAction": null
        },
        "comment": ""
      },
      {
        "supply": "25",
        "time": "2:33",
        "action": "Refinery",
        "interpretedAction": {
          "unitType": 20,
          "upgradeType": null,
          "count": 1,
          "isUpgrade": false,
          "isChronoBoosted": false,
          "specialAction": null
        },
        "comment": ""
      },
      {
        "supply": "26",
        "time": "2:44",
        "action": "Marine x2",
        "interpretedAction": {
          "unitType": 48,
          "upgradeType": null,
          "count": 2,
          "isUpgrade": false,
          "isChronoBoosted": false,
          "specialAction": null
        },
        "comment": ""
      },
      {
        "supply": "29",
        "time": "2:54",
        "action": "Orbital Command",
        "interpretedAction": {
          "unitType": 132,
          "upgradeType": null,
          "count": 1,
          "isUpgrade": false,
          "isChronoBoosted": false,
          "specialAction": null
        },
        "comment": ""
      },
      {
        "supply": "30",
        "time": "3:02",
        "action": "Starport",
        "interpretedAction": {
          "unitType": 28,
          "upgradeType": null,
          "count": 1,
          "isUpgrade": false,
          "isChronoBoosted": false,
          "specialAction": null
        },
        "comment": ""
      },
      {
        "supply": "30",
        "time": "3:05",
        "action": "Factory Tech Lab",
        "interpretedAction": {
          "unitType": 39,
          "upgradeType": null,
          "count": 1,
          "isUpgrade": false,
          "isChronoBoosted": false,
          "specialAction": null
        },
        "comment": ""
      },
      {
        "supply": "31",
        "time": "3:13",
        "action": "Marine x2",
        "interpretedAction": {
          "unitType": 48,
          "upgradeType": null,
          "count": 2,
          "isUpgrade": false,
          "isChronoBoosted": false,
          "specialAction": null
        },
        "comment": ""
      },
      {
        "supply": "34",
        "time": "3:24",
        "action": "Widow Mine",
        "interpretedAction": {
          "unitType": 498,
          "upgradeType": null,
          "count": 1,
          "isUpgrade": false,
          "isChronoBoosted": false,
          "specialAction": null
        },
        "comment": ""
      },
      {
        "supply": "37",
        "time": "3:28",
        "action": "Supply Depot",
        "interpretedAction": {
          "unitType": 19,
          "upgradeType": null,
          "count": 1,
          "isUpgrade": false,
          "isChronoBoosted": false,
          "specialAction": null
        },
        "comment": "CHAIN THOSE!!! xdddd"
      },
      {
        "supply": "39",
        "time": "3:40",
        "action": "Viking",
        "interpretedAction": {
          "unitType": null,
          "upgradeType": null,
          "count": 1,
          "isUpgrade": false,
          "isChronoBoosted": false,
          "specialAction": null
        },
        "comment": ""
      },
      {
        "supply": "41",
        "time": "3:46",
        "action": "Siege Tank",
        "interpretedAction": {
          "unitType": 33,
          "upgradeType": null,
          "count": 1,
          "isUpgrade": false,
          "isChronoBoosted": false,
          "specialAction": null
        },
        "comment": ""
      },
      {
        "supply": "46",
        "time": "3:51",
        "action": "Supply Depot",
        "interpretedAction": {
          "unitType": 19,
          "upgradeType": null,
          "count": 1,
          "isUpgrade": false,
          "isChronoBoosted": false,
          "specialAction": null
        },
        "comment": ""
      },
      {
        "supply": "48",
        "time": "4:05",
        "action": "Barracks x2",
        "interpretedAction": {
          "unitType": 21,
          "upgradeType": null,
          "count": 2,
          "isUpgrade": false,
          "isChronoBoosted": false,
          "specialAction": null
        },
        "comment": ""
      },
      {
        "supply": "50",
        "time": "4:12",
        "action": "Starport Tech Lab",
        "interpretedAction": {
          "unitType": 41,
          "upgradeType": null,
          "count": 1,
          "isUpgrade": false,
          "isChronoBoosted": false,
          "specialAction": null
        },
        "comment": ""
      },
      {
        "supply": "50",
        "time": "4:15",
        "action": "Marine x2",
        "interpretedAction": {
          "unitType": 48,
          "upgradeType": null,
          "count": 2,
          "isUpgrade": false,
          "isChronoBoosted": false,
          "specialAction": null
        },
        "comment": ""
      },
      {
        "supply": "52",
        "time": "4:21",
        "action": "Supply Depot",
        "interpretedAction": {
          "unitType": 19,
          "upgradeType": null,
          "count": 1,
          "isUpgrade": false,
          "isChronoBoosted": false,
          "specialAction": null
        },
        "comment": ""
      },
      {
        "supply": "54",
        "time": "4:28",
        "action": "Factory Tech Lab",
        "interpretedAction": {
          "unitType": 39,
          "upgradeType": null,
          "count": 1,
          "isUpgrade": false,
          "isChronoBoosted": false,
          "specialAction": null
        },
        "comment": ""
      },
      {
        "supply": "54",
        "time": "4:31",
        "action": "Engineering Bay",
        "interpretedAction": {
          "unitType": 22,
          "upgradeType": null,
          "count": 1,
          "isUpgrade": false,
          "isChronoBoosted": false,
          "specialAction": null
        },
        "comment": ""
      },
      {
        "supply": "54",
        "time": "4:36",
        "action": "Refinery",
        "interpretedAction": {
          "unitType": 20,
          "upgradeType": null,
          "count": 1,
          "isUpgrade": false,
          "isChronoBoosted": false,
          "specialAction": null
        },
        "comment": ""
      },
      {
        "supply": "56",
        "time": "4:38",
        "action": "Starport Reactor, Marine",
        "interpretedAction": {
          "unitType": 42,
          "upgradeType": null,
          "count": 1,
          "isUpgrade": false,
          "isChronoBoosted": false,
          "specialAction": null
        },
        "comment": ""
      },
      {
        "supply": "56",
        "time": "4:38",
        "action": "Starport Reactor, Marine",
        "interpretedAction": {
          "unitType": 48,
          "upgradeType": null,
          "count": 1,
          "isUpgrade": false,
          "isChronoBoosted": false,
          "specialAction": null
        },
        "comment": ""
      },
      {
        "supply": "58",
        "time": "4:47",
        "action": "Siege Tank",
        "interpretedAction": {
          "unitType": 33,
          "upgradeType": null,
          "count": 1,
          "isUpgrade": false,
          "isChronoBoosted": false,
          "specialAction": null
        },
        "comment": ""
      },
      {
        "supply": "65",
        "time": "5:02",
        "action": "Refinery",
        "interpretedAction": {
          "unitType": 20,
          "upgradeType": null,
          "count": 1,
          "isUpgrade": false,
          "isChronoBoosted": false,
          "specialAction": null
        },
        "comment": ""
      },
      {
        "supply": "70",
        "time": "5:19",
        "action": "Siege Tank",
        "interpretedAction": {
          "unitType": 33,
          "upgradeType": null,
          "count": 1,
          "isUpgrade": false,
          "isChronoBoosted": false,
          "specialAction": null
        },
        "comment": ""
      },
      {
        "supply": "77",
        "time": "5:41",
        "action": "Command Center",
        "interpretedAction": {
          "unitType": 18,
          "upgradeType": null,
          "count": 1,
          "isUpgrade": false,
          "isChronoBoosted": false,
          "specialAction": null
        },
        "comment": ""
      },
      {
        "supply": "77",
        "time": "5:44",
        "action": "Marauder x2",
        "interpretedAction": {
          "unitType": 51,
          "upgradeType": null,
          "count": 2,
          "isUpgrade": false,
          "isChronoBoosted": false,
          "specialAction": null
        },
        "comment": ""
      },
      {
        "supply": "85",
        "time": "6:17",
        "action": "Marauder x2",
        "interpretedAction": {
          "unitType": 51,
          "upgradeType": null,
          "count": 2,
          "isUpgrade": false,
          "isChronoBoosted": false,
          "specialAction": null
        },
        "comment": ""
      }
    ],
    "raceMatchup": "TvP",
    "url": "https://lotv.spawningtool.com/build/180455/"
  },
  {
    "title": "GreatOz FastestPossibleBC(Battlecruiser)",
    "steps": [
      {
        "supply": "12",
        "time": "0:08",
        "action": "Supply Depot",
        "interpretedAction": {
          "unitType": 19,
          "upgradeType": null,
          "count": 1,
          "isUpgrade": false,
          "isChronoBoosted": false,
          "specialAction": null
        },
        "comment": ""
      },
      {
        "supply": "12",
        "time": "0:16",
        "action": "Refinery",
        "interpretedAction": {
          "unitType": 20,
          "upgradeType": null,
          "count": 1,
          "isUpgrade": false,
          "isChronoBoosted": false,
          "specialAction": null
        },
        "comment": ""
      },
      {
        "supply": "12",
        "time": "0:31",
        "action": "Barracks",
        "interpretedAction": {
          "unitType": 21,
          "upgradeType": null,
          "count": 1,
          "isUpgrade": false,
          "isChronoBoosted": false,
          "specialAction": null
        },
        "comment": ""
      },
      {
        "supply": "12",
        "time": "0:36",
        "action": "SCV",
        "interpretedAction": {
          "unitType": 45,
          "upgradeType": null,
          "count": 1,
          "isUpgrade": false,
          "isChronoBoosted": false,
          "specialAction": null
        },
        "comment": ""
      },
      {
        "supply": "13",
        "time": "0:48",
        "action": "SCV",
        "interpretedAction": {
          "unitType": 45,
          "upgradeType": null,
          "count": 1,
          "isUpgrade": false,
          "isChronoBoosted": false,
          "specialAction": null
        },
        "comment": ""
      },
      {
        "supply": "14",
        "time": "1:00",
        "action": "SCV",
        "interpretedAction": {
          "unitType": 45,
          "upgradeType": null,
          "count": 1,
          "isUpgrade": false,
          "isChronoBoosted": false,
          "specialAction": null
        },
        "comment": ""
      },
      {
        "supply": "15",
        "time": "1:19",
        "action": "Factory",
        "interpretedAction": {
          "unitType": 27,
          "upgradeType": null,
          "count": 1,
          "isUpgrade": false,
          "isChronoBoosted": false,
          "specialAction": null
        },
        "comment": ""
      },
      {
        "supply": "15",
        "time": "1:20",
        "action": "Orbital Command",
        "interpretedAction": {
          "unitType": 132,
          "upgradeType": null,
          "count": 1,
          "isUpgrade": false,
          "isChronoBoosted": false,
          "specialAction": null
        },
        "comment": ""
      },
      {
        "supply": "15",
        "time": "1:27",
        "action": "Refinery",
        "interpretedAction": {
          "unitType": 20,
          "upgradeType": null,
          "count": 1,
          "isUpgrade": false,
          "isChronoBoosted": false,
          "specialAction": null
        },
        "comment": ""
      },
      {
        "supply": "15",
        "time": "1:45",
        "action": "SCV",
        "interpretedAction": {
          "unitType": 45,
          "upgradeType": null,
          "count": 1,
          "isUpgrade": false,
          "isChronoBoosted": false,
          "specialAction": null
        },
        "comment": ""
      },
      {
        "supply": "16",
        "time": "1:57",
        "action": "SCV",
        "interpretedAction": {
          "unitType": 45,
          "upgradeType": null,
          "count": 1,
          "isUpgrade": false,
          "isChronoBoosted": false,
          "specialAction": null
        },
        "comment": ""
      },
      {
        "supply": "17",
        "time": "2:03",
        "action": "Starport",
        "interpretedAction": {
          "unitType": 28,
          "upgradeType": null,
          "count": 1,
          "isUpgrade": false,
          "isChronoBoosted": false,
          "specialAction": null
        },
        "comment": ""
      },
      {
        "supply": "17",
        "time": "2:10",
        "action": "SCV",
        "interpretedAction": {
          "unitType": 45,
          "upgradeType": null,
          "count": 1,
          "isUpgrade": false,
          "isChronoBoosted": false,
          "specialAction": null
        },
        "comment": ""
      },
      {
        "supply": "18",
        "time": "2:22",
        "action": "SCV",
        "interpretedAction": {
          "unitType": 45,
          "upgradeType": null,
          "count": 1,
          "isUpgrade": false,
          "isChronoBoosted": false,
          "specialAction": null
        },
        "comment": ""
      },
      {
        "supply": "19",
        "time": "2:26",
        "action": "Supply Depot",
        "interpretedAction": {
          "unitType": 19,
          "upgradeType": null,
          "count": 1,
          "isUpgrade": false,
          "isChronoBoosted": false,
          "specialAction": null
        },
        "comment": ""
      },
      {
        "supply": "19",
        "time": "2:34",
        "action": "SCV",
        "interpretedAction": {
          "unitType": 45,
          "upgradeType": null,
          "count": 1,
          "isUpgrade": false,
          "isChronoBoosted": false,
          "specialAction": null
        },
        "comment": ""
      },
      {
        "supply": "20",
        "time": "2:39",
        "action": "Fusion Core",
        "interpretedAction": {
          "unitType": 30,
          "upgradeType": null,
          "count": 1,
          "isUpgrade": false,
          "isChronoBoosted": false,
          "specialAction": null
        },
        "comment": ""
      },
      {
        "supply": "20",
        "time": "2:41",
        "action": "Starport Tech Lab",
        "interpretedAction": {
          "unitType": 41,
          "upgradeType": null,
          "count": 1,
          "isUpgrade": false,
          "isChronoBoosted": false,
          "specialAction": null
        },
        "comment": ""
      },
      {
        "supply": "20",
        "time": "2:46",
        "action": "SCV",
        "interpretedAction": {
          "unitType": 45,
          "upgradeType": null,
          "count": 1,
          "isUpgrade": false,
          "isChronoBoosted": false,
          "specialAction": null
        },
        "comment": ""
      },
      {
        "supply": "21",
        "time": "2:58",
        "action": "SCV",
        "interpretedAction": {
          "unitType": 45,
          "upgradeType": null,
          "count": 1,
          "isUpgrade": false,
          "isChronoBoosted": false,
          "specialAction": null
        },
        "comment": ""
      },
      {
        "supply": "23",
        "time": "3:26",
        "action": "Battlecruiser",
        "interpretedAction": {
          "unitType": 57,
          "upgradeType": null,
          "count": 1,
          "isUpgrade": false,
          "isChronoBoosted": false,
          "specialAction": null
        },
        "comment": ""
      },
      {
        "supply": "30",
        "time": "3:28",
        "action": "Supply Depot",
        "interpretedAction": {
          "unitType": 19,
          "upgradeType": null,
          "count": 1,
          "isUpgrade": false,
          "isChronoBoosted": false,
          "specialAction": null
        },
        "comment": ""
      },
      {
        "supply": "30",
        "time": "3:35",
        "action": "Command Center",
        "interpretedAction": {
          "unitType": 18,
          "upgradeType": null,
          "count": 1,
          "isUpgrade": false,
          "isChronoBoosted": false,
          "specialAction": null
        },
        "comment": ""
      },
      {
        "supply": "31",
        "time": "3:51",
        "action": "Supply Depot",
        "interpretedAction": {
          "unitType": 19,
          "upgradeType": null,
          "count": 1,
          "isUpgrade": false,
          "isChronoBoosted": false,
          "specialAction": null
        },
        "comment": ""
      },
      {
        "supply": "33",
        "time": "4:13",
        "action": "Supply Depot",
        "interpretedAction": {
          "unitType": 19,
          "upgradeType": null,
          "count": 1,
          "isUpgrade": false,
          "isChronoBoosted": false,
          "specialAction": null
        },
        "comment": ""
      }
    ],
    "raceMatchup": "TvX",
    "url": "https://lotv.spawningtool.com/build/180430/"
  },
  {
    "title": "Ling Bane Macro Build",
    "steps": [
      {
        "supply": "13",
        "time": "0:00",
        "action": "Drone",
        "interpretedAction": {
          "unitType": 104,
          "upgradeType": null,
          "count": 1,
          "isUpgrade": false,
          "isChronoBoosted": false,
          "specialAction": null
        },
        "comment": ""
      },
      {
        "supply": "13",
        "time": "0:13",
        "action": "Overlord",
        "interpretedAction": {
          "unitType": 106,
          "upgradeType": null,
          "count": 1,
          "isUpgrade": false,
          "isChronoBoosted": false,
          "specialAction": null
        },
        "comment": ""
      },
      {
        "supply": "14",
        "time": "0:17",
        "action": "Drone",
        "interpretedAction": {
          "unitType": 104,
          "upgradeType": null,
          "count": 1,
          "isUpgrade": false,
          "isChronoBoosted": false,
          "specialAction": null
        },
        "comment": ""
      },
      {
        "supply": "14",
        "time": "0:18",
        "action": "Action Waypoint Overlord to Natural and then to the front of the Natural to scout for proxy/cannon",
        "interpretedAction": {
          "unitType": null,
          "upgradeType": null,
          "count": 1,
          "isUpgrade": false,
          "isChronoBoosted": false,
          "specialAction": null
        },
        "comment": ""
      },
      {
        "supply": "15",
        "time": "0:30",
        "action": "Drone x2 waypoint one to natural for hatchery",
        "interpretedAction": {
          "unitType": null,
          "upgradeType": null,
          "count": 2,
          "isUpgrade": false,
          "isChronoBoosted": false,
          "specialAction": null
        },
        "comment": ""
      },
      {
        "supply": "17",
        "time": "0:34",
        "action": "Drone",
        "interpretedAction": {
          "unitType": 104,
          "upgradeType": null,
          "count": 1,
          "isUpgrade": false,
          "isChronoBoosted": false,
          "specialAction": null
        },
        "comment": ""
      },
      {
        "supply": "17",
        "time": "0:35",
        "action": "Action send drone to scout for early aggression (forge, 2 gas, early pool, no buildings)",
        "interpretedAction": {
          "unitType": null,
          "upgradeType": null,
          "count": 1,
          "isUpgrade": false,
          "isChronoBoosted": false,
          "specialAction": null
        },
        "comment": ""
      },
      {
        "supply": "17",
        "time": "0:35",
        "action": "Action send drone to scout for early aggression (forge, 2 gas, early pool, no buildings)",
        "interpretedAction": {
          "unitType": null,
          "upgradeType": null,
          "count": 1,
          "isUpgrade": false,
          "isChronoBoosted": false,
          "specialAction": null
        },
        "comment": ""
      },
      {
        "supply": "17",
        "time": "0:35",
        "action": "Action send drone to scout for early aggression (forge, 2 gas, early pool, no buildings)",
        "interpretedAction": {
          "unitType": null,
          "upgradeType": null,
          "count": 1,
          "isUpgrade": false,
          "isChronoBoosted": false,
          "specialAction": null
        },
        "comment": ""
      },
      {
        "supply": "17",
        "time": "0:35",
        "action": "Action send drone to scout for early aggression (forge, 2 gas, early pool, no buildings)",
        "interpretedAction": {
          "unitType": null,
          "upgradeType": null,
          "count": 1,
          "isUpgrade": false,
          "isChronoBoosted": false,
          "specialAction": null
        },
        "comment": ""
      },
      {
        "supply": "17",
        "time": "0:52",
        "action": "Hatchery",
        "interpretedAction": {
          "unitType": 86,
          "upgradeType": null,
          "count": 1,
          "isUpgrade": false,
          "isChronoBoosted": false,
          "specialAction": null
        },
        "comment": ""
      },
      {
        "supply": "17",
        "time": "0:55",
        "action": "Drone waypoint to extractor",
        "interpretedAction": {
          "unitType": null,
          "upgradeType": null,
          "count": 1,
          "isUpgrade": false,
          "isChronoBoosted": false,
          "specialAction": null
        },
        "comment": ""
      },
      {
        "supply": "18",
        "time": "0:59",
        "action": "Drone waypoint to spawning pool",
        "interpretedAction": {
          "unitType": null,
          "upgradeType": null,
          "count": 1,
          "isUpgrade": false,
          "isChronoBoosted": false,
          "specialAction": null
        },
        "comment": ""
      },
      {
        "supply": "17",
        "time": "1:09",
        "action": "Extractor",
        "interpretedAction": {
          "unitType": 88,
          "upgradeType": null,
          "count": 1,
          "isUpgrade": false,
          "isChronoBoosted": false,
          "specialAction": null
        },
        "comment": ""
      },
      {
        "supply": "16",
        "time": "1:14",
        "action": "Spawning Pool",
        "interpretedAction": {
          "unitType": 89,
          "upgradeType": null,
          "count": 1,
          "isUpgrade": false,
          "isChronoBoosted": false,
          "specialAction": null
        },
        "comment": ""
      },
      {
        "supply": "17",
        "time": "1:17",
        "action": "Drone",
        "interpretedAction": {
          "unitType": 104,
          "upgradeType": null,
          "count": 1,
          "isUpgrade": false,
          "isChronoBoosted": false,
          "specialAction": null
        },
        "comment": ""
      },
      {
        "supply": "18",
        "time": "1:20",
        "action": "Drone",
        "interpretedAction": {
          "unitType": 104,
          "upgradeType": null,
          "count": 1,
          "isUpgrade": false,
          "isChronoBoosted": false,
          "specialAction": null
        },
        "comment": ""
      },
      {
        "supply": "19",
        "time": "1:27",
        "action": "Drone",
        "interpretedAction": {
          "unitType": 104,
          "upgradeType": null,
          "count": 1,
          "isUpgrade": false,
          "isChronoBoosted": false,
          "specialAction": null
        },
        "comment": ""
      },
      {
        "supply": "19",
        "time": "1:29",
        "action": "Action Move 3 drones from minerals to gas",
        "interpretedAction": {
          "unitType": null,
          "upgradeType": null,
          "count": 1,
          "isUpgrade": false,
          "isChronoBoosted": false,
          "specialAction": null
        },
        "comment": ""
      },
      {
        "supply": "19",
        "time": "1:38",
        "action": "Overlord",
        "interpretedAction": {
          "unitType": 106,
          "upgradeType": null,
          "count": 1,
          "isUpgrade": false,
          "isChronoBoosted": false,
          "specialAction": null
        },
        "comment": ""
      },
      {
        "supply": "20",
        "time": "1:49",
        "action": "Drone",
        "interpretedAction": {
          "unitType": 104,
          "upgradeType": null,
          "count": 1,
          "isUpgrade": false,
          "isChronoBoosted": false,
          "specialAction": null
        },
        "comment": ""
      },
      {
        "supply": "22",
        "time": "2:04",
        "action": "Zergling x2, Queen x2",
        "interpretedAction": {
          "unitType": 105,
          "upgradeType": null,
          "count": 2,
          "isUpgrade": false,
          "isChronoBoosted": false,
          "specialAction": null
        },
        "comment": ""
      },
      {
        "supply": "22",
        "time": "2:04",
        "action": "Zergling x2, Queen x2",
        "interpretedAction": {
          "unitType": 126,
          "upgradeType": null,
          "count": 2,
          "isUpgrade": false,
          "isChronoBoosted": false,
          "specialAction": null
        },
        "comment": ""
      },
      {
        "supply": "27",
        "time": "2:10",
        "action": "Drone",
        "interpretedAction": {
          "unitType": 104,
          "upgradeType": null,
          "count": 1,
          "isUpgrade": false,
          "isChronoBoosted": false,
          "specialAction": null
        },
        "comment": ""
      },
      {
        "supply": "28",
        "time": "2:16",
        "action": "Drone",
        "interpretedAction": {
          "unitType": 104,
          "upgradeType": null,
          "count": 1,
          "isUpgrade": false,
          "isChronoBoosted": false,
          "specialAction": null
        },
        "comment": ""
      },
      {
        "supply": "29",
        "time": "2:22",
        "action": "Drone",
        "interpretedAction": {
          "unitType": 104,
          "upgradeType": null,
          "count": 1,
          "isUpgrade": false,
          "isChronoBoosted": false,
          "specialAction": null
        },
        "comment": ""
      },
      {
        "supply": "30",
        "time": "2:25",
        "action": "Drone",
        "interpretedAction": {
          "unitType": 104,
          "upgradeType": null,
          "count": 1,
          "isUpgrade": false,
          "isChronoBoosted": false,
          "specialAction": null
        },
        "comment": ""
      },
      {
        "supply": "30",
        "time": "2:26",
        "action": "Action send drone to 3rd for hatch",
        "interpretedAction": {
          "unitType": null,
          "upgradeType": null,
          "count": 1,
          "isUpgrade": false,
          "isChronoBoosted": false,
          "specialAction": null
        },
        "comment": ""
      },
      {
        "supply": "31",
        "time": "2:32",
        "action": "Drone",
        "interpretedAction": {
          "unitType": 104,
          "upgradeType": null,
          "count": 1,
          "isUpgrade": false,
          "isChronoBoosted": false,
          "specialAction": null
        },
        "comment": ""
      },
      {
        "supply": "32",
        "time": "2:36",
        "action": "Drone",
        "interpretedAction": {
          "unitType": 104,
          "upgradeType": null,
          "count": 1,
          "isUpgrade": false,
          "isChronoBoosted": false,
          "specialAction": null
        },
        "comment": ""
      },
      {
        "supply": "31",
        "time": "2:38",
        "action": "Hatchery",
        "interpretedAction": {
          "unitType": 86,
          "upgradeType": null,
          "count": 1,
          "isUpgrade": false,
          "isChronoBoosted": false,
          "specialAction": null
        },
        "comment": ""
      },
      {
        "supply": "31",
        "time": "2:40",
        "action": "Action Injects",
        "interpretedAction": {
          "unitType": null,
          "upgradeType": null,
          "count": 1,
          "isUpgrade": false,
          "isChronoBoosted": false,
          "specialAction": null
        },
        "comment": ""
      },
      {
        "supply": "33",
        "time": "2:48",
        "action": "Queen from natural",
        "interpretedAction": {
          "unitType": null,
          "upgradeType": null,
          "count": 1,
          "isUpgrade": false,
          "isChronoBoosted": false,
          "specialAction": null
        },
        "comment": ""
      },
      {
        "supply": "33",
        "time": "2:55",
        "action": "Overlord timing tbc",
        "interpretedAction": {
          "unitType": null,
          "upgradeType": null,
          "count": 1,
          "isUpgrade": false,
          "isChronoBoosted": false,
          "specialAction": null
        },
        "comment": ""
      },
      {
        "supply": "35",
        "time": "2:58",
        "action": "Drone timing tbc",
        "interpretedAction": {
          "unitType": null,
          "upgradeType": null,
          "count": 1,
          "isUpgrade": false,
          "isChronoBoosted": false,
          "specialAction": null
        },
        "comment": ""
      },
      {
        "supply": "36",
        "time": "2:59",
        "action": "Drone timing tbc",
        "interpretedAction": {
          "unitType": null,
          "upgradeType": null,
          "count": 1,
          "isUpgrade": false,
          "isChronoBoosted": false,
          "specialAction": null
        },
        "comment": ""
      },
      {
        "supply": "36",
        "time": "3:04",
        "action": "Metabolic Boost timing tbc",
        "interpretedAction": {
          "unitType": null,
          "upgradeType": null,
          "count": 1,
          "isUpgrade": false,
          "isChronoBoosted": false,
          "specialAction": null
        },
        "comment": ""
      },
      {
        "supply": "36",
        "time": "3:12",
        "action": "Action inject",
        "interpretedAction": {
          "unitType": null,
          "upgradeType": null,
          "count": 1,
          "isUpgrade": false,
          "isChronoBoosted": false,
          "specialAction": null
        },
        "comment": ""
      },
      {
        "supply": "36",
        "time": "3:14",
        "action": "Lair timing tbc",
        "interpretedAction": {
          "unitType": null,
          "upgradeType": null,
          "count": 1,
          "isUpgrade": false,
          "isChronoBoosted": false,
          "specialAction": null
        },
        "comment": ""
      },
      {
        "supply": "36",
        "time": "3:23",
        "action": "Overlord x2 timing tbc",
        "interpretedAction": {
          "unitType": null,
          "upgradeType": null,
          "count": 2,
          "isUpgrade": false,
          "isChronoBoosted": false,
          "specialAction": null
        },
        "comment": ""
      },
      {
        "supply": "37",
        "time": "3:10",
        "action": "Drone timing tbc",
        "interpretedAction": {
          "unitType": null,
          "upgradeType": null,
          "count": 1,
          "isUpgrade": false,
          "isChronoBoosted": false,
          "specialAction": null
        },
        "comment": ""
      }
    ],
    "raceMatchup": "ZvX",
    "url": "https://lotv.spawningtool.com/build/180400/"
  },
  {
    "title": "[3v3] <Imxl>Future Cyclone/Banshee (IcebergSlim)",
    "steps": [
      {
        "supply": "14",
        "time": "0:17",
        "action": "Supply Depot",
        "interpretedAction": {
          "unitType": 19,
          "upgradeType": null,
          "count": 1,
          "isUpgrade": false,
          "isChronoBoosted": false,
          "specialAction": null
        },
        "comment": "> Refinery"
      },
      {
        "supply": "17",
        "time": "1:02",
        "action": "Command Center",
        "interpretedAction": {
          "unitType": 18,
          "upgradeType": null,
          "count": 1,
          "isUpgrade": false,
          "isChronoBoosted": false,
          "specialAction": null
        },
        "comment": "CC #2"
      },
      {
        "supply": "18",
        "time": "1:14",
        "action": "Barracks",
        "interpretedAction": {
          "unitType": 21,
          "upgradeType": null,
          "count": 1,
          "isUpgrade": false,
          "isChronoBoosted": false,
          "specialAction": null
        },
        "comment": ""
      },
      {
        "supply": "19",
        "time": "1:22",
        "action": "Refinery",
        "interpretedAction": {
          "unitType": 20,
          "upgradeType": null,
          "count": 1,
          "isUpgrade": false,
          "isChronoBoosted": false,
          "specialAction": null
        },
        "comment": "Refinery #1"
      },
      {
        "supply": "20",
        "time": "1:32",
        "action": "Refinery",
        "interpretedAction": {
          "unitType": 20,
          "upgradeType": null,
          "count": 1,
          "isUpgrade": false,
          "isChronoBoosted": false,
          "specialAction": null
        },
        "comment": "Refinery #2"
      },
      {
        "supply": "21",
        "time": "2:01",
        "action": "Marine",
        "interpretedAction": {
          "unitType": 48,
          "upgradeType": null,
          "count": 1,
          "isUpgrade": false,
          "isChronoBoosted": false,
          "specialAction": null
        },
        "comment": ""
      },
      {
        "supply": "23",
        "time": "2:08",
        "action": "Orbital Command",
        "interpretedAction": {
          "unitType": 132,
          "upgradeType": null,
          "count": 1,
          "isUpgrade": false,
          "isChronoBoosted": false,
          "specialAction": null
        },
        "comment": ""
      },
      {
        "supply": "23",
        "time": "2:11",
        "action": "Factory",
        "interpretedAction": {
          "unitType": 27,
          "upgradeType": null,
          "count": 1,
          "isUpgrade": false,
          "isChronoBoosted": false,
          "specialAction": null
        },
        "comment": "build next to rax"
      },
      {
        "supply": "23",
        "time": "2:22",
        "action": "Barracks Reactor",
        "interpretedAction": {
          "unitType": 38,
          "upgradeType": null,
          "count": 1,
          "isUpgrade": false,
          "isChronoBoosted": false,
          "specialAction": null
        },
        "comment": ""
      },
      {
        "supply": "23",
        "time": "2:31",
        "action": "Refinery",
        "interpretedAction": {
          "unitType": 20,
          "upgradeType": null,
          "count": 1,
          "isUpgrade": false,
          "isChronoBoosted": false,
          "specialAction": null
        },
        "comment": "Refinery #3"
      },
      {
        "supply": "23",
        "time": "2:17",
        "action": "Orbital Command",
        "interpretedAction": {
          "unitType": 132,
          "upgradeType": null,
          "count": 1,
          "isUpgrade": false,
          "isChronoBoosted": false,
          "specialAction": null
        },
        "comment": ""
      },
      {
        "supply": "28",
        "time": "3:01",
        "action": "Starport x2",
        "interpretedAction": {
          "unitType": 28,
          "upgradeType": null,
          "count": 2,
          "isUpgrade": false,
          "isChronoBoosted": false,
          "specialAction": null
        },
        "comment": ""
      },
      {
        "supply": "28",
        "time": "3:05",
        "action": "Hellion",
        "interpretedAction": {
          "unitType": 53,
          "upgradeType": null,
          "count": 1,
          "isUpgrade": false,
          "isChronoBoosted": false,
          "specialAction": null
        },
        "comment": "after swapping factor w/ rax"
      },
      {
        "supply": "31",
        "time": "3:19",
        "action": "Supply Depot",
        "interpretedAction": {
          "unitType": 19,
          "upgradeType": null,
          "count": 1,
          "isUpgrade": false,
          "isChronoBoosted": false,
          "specialAction": null
        },
        "comment": "> depots.. (dedicated depot scv)"
      },
      {
        "supply": "32",
        "time": "3:30",
        "action": "Cyclone x2",
        "interpretedAction": {
          "unitType": 692,
          "upgradeType": null,
          "count": 2,
          "isUpgrade": false,
          "isChronoBoosted": false,
          "specialAction": null
        },
        "comment": ""
      },
      {
        "supply": "38",
        "time": "3:40",
        "action": "Starport Tech Lab x2",
        "interpretedAction": {
          "unitType": 41,
          "upgradeType": null,
          "count": 2,
          "isUpgrade": false,
          "isChronoBoosted": false,
          "specialAction": null
        },
        "comment": ""
      },
      {
        "supply": "43",
        "time": "4:05",
        "action": "Banshee x2",
        "interpretedAction": {
          "unitType": 55,
          "upgradeType": null,
          "count": 2,
          "isUpgrade": false,
          "isChronoBoosted": false,
          "specialAction": null
        },
        "comment": ""
      },
      {
        "supply": "50",
        "time": "4:18",
        "action": "Cyclone x2",
        "interpretedAction": {
          "unitType": 692,
          "upgradeType": null,
          "count": 2,
          "isUpgrade": false,
          "isChronoBoosted": false,
          "specialAction": null
        },
        "comment": ""
      },
      {
        "supply": "59",
        "time": "4:42",
        "action": "Hyperflight Rotors",
        "interpretedAction": {
          "unitType": null,
          "upgradeType": null,
          "count": 1,
          "isUpgrade": false,
          "isChronoBoosted": false,
          "specialAction": null
        },
        "comment": ""
      },
      {
        "supply": "59",
        "time": "4:51",
        "action": "Banshee x2",
        "interpretedAction": {
          "unitType": 55,
          "upgradeType": null,
          "count": 2,
          "isUpgrade": false,
          "isChronoBoosted": false,
          "specialAction": null
        },
        "comment": ""
      },
      {
        "supply": "67",
        "time": "4:56",
        "action": "Refinery",
        "interpretedAction": {
          "unitType": 20,
          "upgradeType": null,
          "count": 1,
          "isUpgrade": false,
          "isChronoBoosted": false,
          "specialAction": null
        },
        "comment": "Refinery #4"
      },
      {
        "supply": "67",
        "time": "5:01",
        "action": "Cyclone",
        "interpretedAction": {
          "unitType": 692,
          "upgradeType": null,
          "count": 1,
          "isUpgrade": false,
          "isChronoBoosted": false,
          "specialAction": null
        },
        "comment": ""
      },
      {
        "supply": "71",
        "time": "5:03",
        "action": "Cloaking Field",
        "interpretedAction": {
          "unitType": null,
          "upgradeType": null,
          "count": 1,
          "isUpgrade": false,
          "isChronoBoosted": false,
          "specialAction": null
        },
        "comment": ""
      }
    ],
    "raceMatchup": "TvX",
    "url": "https://lotv.spawningtool.com/build/180369/"
  },
  {
    "title": "Serral ZvP vs SG into 3base Stalkers",
    "steps": [
      {
        "supply": "14",
        "time": "0:30",
        "action": "Hatchery",
        "interpretedAction": {
          "unitType": 86,
          "upgradeType": null,
          "count": 1,
          "isUpgrade": false,
          "isChronoBoosted": false,
          "specialAction": null
        },
        "comment": ""
      },
      {
        "supply": "14",
        "time": "0:44",
        "action": "Extractor",
        "interpretedAction": {
          "unitType": 88,
          "upgradeType": null,
          "count": 1,
          "isUpgrade": false,
          "isChronoBoosted": false,
          "specialAction": null
        },
        "comment": "Extractor trick to build drone"
      },
      {
        "supply": "15",
        "time": "0:49",
        "action": "Overlord",
        "interpretedAction": {
          "unitType": 106,
          "upgradeType": null,
          "count": 1,
          "isUpgrade": false,
          "isChronoBoosted": false,
          "specialAction": null
        },
        "comment": ""
      },
      {
        "supply": "15",
        "time": "1:04",
        "action": "Spawning Pool",
        "interpretedAction": {
          "unitType": 89,
          "upgradeType": null,
          "count": 1,
          "isUpgrade": false,
          "isChronoBoosted": false,
          "specialAction": null
        },
        "comment": ""
      },
      {
        "supply": "18",
        "time": "1:30",
        "action": "Extractor",
        "interpretedAction": {
          "unitType": 88,
          "upgradeType": null,
          "count": 1,
          "isUpgrade": false,
          "isChronoBoosted": false,
          "specialAction": null
        },
        "comment": "use 17th drone, next 2 drones rally to natural, 20th drone rally to gas"
      },
      {
        "supply": "20",
        "time": "1:51",
        "action": "Queen x2",
        "interpretedAction": {
          "unitType": 126,
          "upgradeType": null,
          "count": 2,
          "isUpgrade": false,
          "isChronoBoosted": false,
          "specialAction": null
        },
        "comment": "25/28 drone @ main rally to gas + 2 lings @ nat"
      },
      {
        "supply": "30",
        "time": "2:30",
        "action": "Hatchery",
        "interpretedAction": {
          "unitType": 86,
          "upgradeType": null,
          "count": 1,
          "isUpgrade": false,
          "isChronoBoosted": false,
          "specialAction": null
        },
        "comment": "+ 2 Lings @ main"
      },
      {
        "supply": "31",
        "time": "2:40",
        "action": "Overlord",
        "interpretedAction": {
          "unitType": 106,
          "upgradeType": null,
          "count": 1,
          "isUpgrade": false,
          "isChronoBoosted": false,
          "specialAction": null
        },
        "comment": ""
      },
      {
        "supply": "31",
        "time": "2:43",
        "action": "Queen",
        "interpretedAction": {
          "unitType": 126,
          "upgradeType": null,
          "count": 1,
          "isUpgrade": false,
          "isChronoBoosted": false,
          "specialAction": null
        },
        "comment": "@ 100 gas move 2 drones to natural"
      },
      {
        "supply": "34",
        "time": "2:54",
        "action": "Metabolic Boost",
        "interpretedAction": {
          "unitType": null,
          "upgradeType": null,
          "count": 1,
          "isUpgrade": false,
          "isChronoBoosted": false,
          "specialAction": null
        },
        "comment": "morph 3 larva from 1st inject @ main into drones & rally to gas"
      },
      {
        "supply": "37",
        "time": "3:05",
        "action": "Overlord",
        "interpretedAction": {
          "unitType": 106,
          "upgradeType": null,
          "count": 1,
          "isUpgrade": false,
          "isChronoBoosted": false,
          "specialAction": null
        },
        "comment": ""
      },
      {
        "supply": "41",
        "time": "3:20",
        "action": "Queen",
        "interpretedAction": {
          "unitType": 126,
          "upgradeType": null,
          "count": 1,
          "isUpgrade": false,
          "isChronoBoosted": false,
          "specialAction": null
        },
        "comment": "@ main"
      },
      {
        "supply": "45",
        "time": "3:28",
        "action": "Queen",
        "interpretedAction": {
          "unitType": 126,
          "upgradeType": null,
          "count": 1,
          "isUpgrade": false,
          "isChronoBoosted": false,
          "specialAction": null
        },
        "comment": "@ natural +6 Lings @ main"
      },
      {
        "supply": "49",
        "time": "3:38",
        "action": "Overlord",
        "interpretedAction": {
          "unitType": 106,
          "upgradeType": null,
          "count": 1,
          "isUpgrade": false,
          "isChronoBoosted": false,
          "specialAction": null
        },
        "comment": ""
      },
      {
        "supply": "50",
        "time": "3:39",
        "action": "Overlord",
        "interpretedAction": {
          "unitType": 106,
          "upgradeType": null,
          "count": 1,
          "isUpgrade": false,
          "isChronoBoosted": false,
          "specialAction": null
        },
        "comment": ""
      },
      {
        "supply": "52",
        "time": "3:50",
        "action": "Queen",
        "interpretedAction": {
          "unitType": 126,
          "upgradeType": null,
          "count": 1,
          "isUpgrade": false,
          "isChronoBoosted": false,
          "specialAction": null
        },
        "comment": "@ 3rd"
      },
      {
        "supply": "57",
        "time": "4:00",
        "action": "Spore Crawler x2",
        "interpretedAction": {
          "unitType": 99,
          "upgradeType": null,
          "count": 2,
          "isUpgrade": false,
          "isChronoBoosted": false,
          "specialAction": null
        },
        "comment": "@ main & nat"
      },
      {
        "supply": "62",
        "time": "4:15",
        "action": "Overlord",
        "interpretedAction": {
          "unitType": 106,
          "upgradeType": null,
          "count": 1,
          "isUpgrade": false,
          "isChronoBoosted": false,
          "specialAction": null
        },
        "comment": "+2 Lings"
      },
      {
        "supply": "66",
        "time": "4:25",
        "action": "Overlord",
        "interpretedAction": {
          "unitType": 106,
          "upgradeType": null,
          "count": 1,
          "isUpgrade": false,
          "isChronoBoosted": false,
          "specialAction": null
        },
        "comment": "+2 Lings"
      },
      {
        "supply": "71",
        "time": "4:30",
        "action": "Roach Warren",
        "interpretedAction": {
          "unitType": 97,
          "upgradeType": null,
          "count": 1,
          "isUpgrade": false,
          "isChronoBoosted": false,
          "specialAction": null
        },
        "comment": ""
      },
      {
        "supply": "76",
        "time": "4:45",
        "action": "Lair",
        "interpretedAction": {
          "unitType": 100,
          "upgradeType": null,
          "count": 1,
          "isUpgrade": false,
          "isChronoBoosted": false,
          "specialAction": null
        },
        "comment": "+ 2 Lings"
      },
      {
        "supply": "82",
        "time": "5:00",
        "action": "Extractor x2",
        "interpretedAction": {
          "unitType": 88,
          "upgradeType": null,
          "count": 2,
          "isUpgrade": false,
          "isChronoBoosted": false,
          "specialAction": null
        },
        "comment": ""
      },
      {
        "supply": "81",
        "time": "5:01",
        "action": "Evolution Chamber",
        "interpretedAction": {
          "unitType": 90,
          "upgradeType": null,
          "count": 1,
          "isUpgrade": false,
          "isChronoBoosted": false,
          "specialAction": null
        },
        "comment": ""
      },
      {
        "supply": "84",
        "time": "5:20",
        "action": "Hatchery",
        "interpretedAction": {
          "unitType": 86,
          "upgradeType": null,
          "count": 1,
          "isUpgrade": false,
          "isChronoBoosted": false,
          "specialAction": null
        },
        "comment": ""
      },
      {
        "supply": "83",
        "time": "5:21",
        "action": "Overlord",
        "interpretedAction": {
          "unitType": 106,
          "upgradeType": null,
          "count": 1,
          "isUpgrade": false,
          "isChronoBoosted": false,
          "specialAction": null
        },
        "comment": ""
      },
      {
        "supply": "88",
        "time": "5:25",
        "action": "Extractor",
        "interpretedAction": {
          "unitType": 88,
          "upgradeType": null,
          "count": 1,
          "isUpgrade": false,
          "isChronoBoosted": false,
          "specialAction": null
        },
        "comment": ""
      },
      {
        "supply": "88",
        "time": "5:26",
        "action": "Overlord",
        "interpretedAction": {
          "unitType": 106,
          "upgradeType": null,
          "count": 1,
          "isUpgrade": false,
          "isChronoBoosted": false,
          "specialAction": null
        },
        "comment": ""
      },
      {
        "supply": "88",
        "time": "5:27",
        "action": "Overlord",
        "interpretedAction": {
          "unitType": 106,
          "upgradeType": null,
          "count": 1,
          "isUpgrade": false,
          "isChronoBoosted": false,
          "specialAction": null
        },
        "comment": ""
      },
      {
        "supply": "90",
        "time": "5:30",
        "action": "Extractor x2",
        "interpretedAction": {
          "unitType": 88,
          "upgradeType": null,
          "count": 2,
          "isUpgrade": false,
          "isChronoBoosted": false,
          "specialAction": null
        },
        "comment": ""
      },
      {
        "supply": "88",
        "time": "5:31",
        "action": "Zerg Missile Weapons Level 1",
        "interpretedAction": {
          "unitType": null,
          "upgradeType": null,
          "count": 1,
          "isUpgrade": false,
          "isChronoBoosted": false,
          "specialAction": null
        },
        "comment": ""
      },
      {
        "supply": "88",
        "time": "5:33",
        "action": "Overlord",
        "interpretedAction": {
          "unitType": 106,
          "upgradeType": null,
          "count": 1,
          "isUpgrade": false,
          "isChronoBoosted": false,
          "specialAction": null
        },
        "comment": ""
      },
      {
        "supply": "87",
        "time": "5:40",
        "action": "Spore Crawler",
        "interpretedAction": {
          "unitType": 99,
          "upgradeType": null,
          "count": 1,
          "isUpgrade": false,
          "isChronoBoosted": false,
          "specialAction": null
        },
        "comment": "@ 3rd"
      },
      {
        "supply": "89",
        "time": "5:45",
        "action": "Hydralisk Den",
        "interpretedAction": {
          "unitType": 91,
          "upgradeType": null,
          "count": 1,
          "isUpgrade": false,
          "isChronoBoosted": false,
          "specialAction": null
        },
        "comment": "start zerlings x7 + 2 Overs, pause droning (should have 68 or 69 drones)"
      },
      {
        "supply": "95",
        "time": "5:55",
        "action": "Overlord",
        "interpretedAction": {
          "unitType": 106,
          "upgradeType": null,
          "count": 1,
          "isUpgrade": false,
          "isChronoBoosted": false,
          "specialAction": null
        },
        "comment": ""
      },
      {
        "supply": "95",
        "time": "6:00",
        "action": "Overlord",
        "interpretedAction": {
          "unitType": 106,
          "upgradeType": null,
          "count": 1,
          "isUpgrade": false,
          "isChronoBoosted": false,
          "specialAction": null
        },
        "comment": ""
      },
      {
        "supply": "99",
        "time": "6:09",
        "action": "Infestation Pit",
        "interpretedAction": {
          "unitType": 94,
          "upgradeType": null,
          "count": 1,
          "isUpgrade": false,
          "isChronoBoosted": false,
          "specialAction": null
        },
        "comment": "+ Over"
      },
      {
        "supply": "98",
        "time": "6:20",
        "action": "Grooved Spines",
        "interpretedAction": {
          "unitType": null,
          "upgradeType": null,
          "count": 1,
          "isUpgrade": false,
          "isChronoBoosted": false,
          "specialAction": null
        },
        "comment": "+ Start Hydra production"
      }
    ],
    "raceMatchup": "ZvP",
    "url": "https://lotv.spawningtool.com/build/180327/"
  },
  {
    "title": "[3v3][ZvX] Dark Hydra/Ling/Bane (IcebergSlim Mod)",
    "steps": [
      {
        "supply": "12",
        "time": "0:00",
        "action": "Drone",
        "interpretedAction": {
          "unitType": 104,
          "upgradeType": null,
          "count": 1,
          "isUpgrade": false,
          "isChronoBoosted": false,
          "specialAction": null
        },
        "comment": ""
      },
      {
        "supply": "13",
        "time": "0:13",
        "action": "Overlord",
        "interpretedAction": {
          "unitType": 106,
          "upgradeType": null,
          "count": 1,
          "isUpgrade": false,
          "isChronoBoosted": false,
          "specialAction": null
        },
        "comment": ""
      },
      {
        "supply": "13",
        "time": "0:18",
        "action": "Drone",
        "interpretedAction": {
          "unitType": 104,
          "upgradeType": null,
          "count": 1,
          "isUpgrade": false,
          "isChronoBoosted": false,
          "specialAction": null
        },
        "comment": ""
      },
      {
        "supply": "14",
        "time": "0:31",
        "action": "Drone x3",
        "interpretedAction": {
          "unitType": 104,
          "upgradeType": null,
          "count": 3,
          "isUpgrade": false,
          "isChronoBoosted": false,
          "specialAction": null
        },
        "comment": ""
      },
      {
        "supply": "17",
        "time": "0:53",
        "action": "Hatchery",
        "interpretedAction": {
          "unitType": 86,
          "upgradeType": null,
          "count": 1,
          "isUpgrade": false,
          "isChronoBoosted": false,
          "specialAction": null
        },
        "comment": ""
      },
      {
        "supply": "17",
        "time": "0:56",
        "action": "Drone x2",
        "interpretedAction": {
          "unitType": 104,
          "upgradeType": null,
          "count": 2,
          "isUpgrade": false,
          "isChronoBoosted": false,
          "specialAction": null
        },
        "comment": ""
      },
      {
        "supply": "18",
        "time": "1:10",
        "action": "Extractor",
        "interpretedAction": {
          "unitType": 88,
          "upgradeType": null,
          "count": 1,
          "isUpgrade": false,
          "isChronoBoosted": false,
          "specialAction": null
        },
        "comment": ""
      },
      {
        "supply": "17",
        "time": "1:15",
        "action": "Spawning Pool",
        "interpretedAction": {
          "unitType": 89,
          "upgradeType": null,
          "count": 1,
          "isUpgrade": false,
          "isChronoBoosted": false,
          "specialAction": null
        },
        "comment": ""
      },
      {
        "supply": "17",
        "time": "1:17",
        "action": "Drone x2",
        "interpretedAction": {
          "unitType": 104,
          "upgradeType": null,
          "count": 2,
          "isUpgrade": false,
          "isChronoBoosted": false,
          "specialAction": null
        },
        "comment": ""
      },
      {
        "supply": "18",
        "time": "1:29",
        "action": "Drone",
        "interpretedAction": {
          "unitType": 104,
          "upgradeType": null,
          "count": 1,
          "isUpgrade": false,
          "isChronoBoosted": false,
          "specialAction": null
        },
        "comment": ""
      },
      {
        "supply": "20",
        "time": "1:47",
        "action": "Hatchery",
        "interpretedAction": {
          "unitType": 86,
          "upgradeType": null,
          "count": 1,
          "isUpgrade": false,
          "isChronoBoosted": false,
          "specialAction": null
        },
        "comment": ""
      },
      {
        "supply": "20",
        "time": "2:06",
        "action": "Queen",
        "interpretedAction": {
          "unitType": 126,
          "upgradeType": null,
          "count": 1,
          "isUpgrade": false,
          "isChronoBoosted": false,
          "specialAction": null
        },
        "comment": ""
      },
      {
        "supply": "24",
        "time": "2:18",
        "action": "Queen",
        "interpretedAction": {
          "unitType": 126,
          "upgradeType": null,
          "count": 1,
          "isUpgrade": false,
          "isChronoBoosted": false,
          "specialAction": null
        },
        "comment": ""
      },
      {
        "supply": "26",
        "time": "2:24",
        "action": "Overlord",
        "interpretedAction": {
          "unitType": 106,
          "upgradeType": null,
          "count": 1,
          "isUpgrade": false,
          "isChronoBoosted": false,
          "specialAction": null
        },
        "comment": ""
      },
      {
        "supply": "28",
        "time": "2:43",
        "action": "Metabolic Boost",
        "interpretedAction": {
          "unitType": null,
          "upgradeType": null,
          "count": 1,
          "isUpgrade": false,
          "isChronoBoosted": false,
          "specialAction": null
        },
        "comment": "pull 2 drones off gas"
      },
      {
        "supply": "31",
        "time": "2:46",
        "action": "Zergling x2",
        "interpretedAction": {
          "unitType": 105,
          "upgradeType": null,
          "count": 2,
          "isUpgrade": false,
          "isChronoBoosted": false,
          "specialAction": null
        },
        "comment": ""
      },
      {
        "supply": "32",
        "time": "2:54",
        "action": "Queen",
        "interpretedAction": {
          "unitType": 126,
          "upgradeType": null,
          "count": 1,
          "isUpgrade": false,
          "isChronoBoosted": false,
          "specialAction": null
        },
        "comment": ""
      },
      {
        "supply": "36",
        "time": "3:02",
        "action": "Queen",
        "interpretedAction": {
          "unitType": 126,
          "upgradeType": null,
          "count": 1,
          "isUpgrade": false,
          "isChronoBoosted": false,
          "specialAction": null
        },
        "comment": ""
      },
      {
        "supply": "42",
        "time": "3:21",
        "action": "Overlord x2",
        "interpretedAction": {
          "unitType": 106,
          "upgradeType": null,
          "count": 2,
          "isUpgrade": false,
          "isChronoBoosted": false,
          "specialAction": null
        },
        "comment": ""
      },
      {
        "supply": "42",
        "time": "3:33",
        "action": "Overlord",
        "interpretedAction": {
          "unitType": 106,
          "upgradeType": null,
          "count": 1,
          "isUpgrade": false,
          "isChronoBoosted": false,
          "specialAction": null
        },
        "comment": ""
      },
      {
        "supply": "42",
        "time": "3:40",
        "action": "Lair",
        "interpretedAction": {
          "unitType": 100,
          "upgradeType": null,
          "count": 1,
          "isUpgrade": false,
          "isChronoBoosted": false,
          "specialAction": null
        },
        "comment": ""
      },
      {
        "supply": "50",
        "time": "3:52",
        "action": "Spore Crawler x2",
        "interpretedAction": {
          "unitType": 99,
          "upgradeType": null,
          "count": 2,
          "isUpgrade": false,
          "isChronoBoosted": false,
          "specialAction": null
        },
        "comment": ""
      },
      {
        "supply": "52",
        "time": "4:04",
        "action": "Extractor",
        "interpretedAction": {
          "unitType": 88,
          "upgradeType": null,
          "count": 1,
          "isUpgrade": false,
          "isChronoBoosted": false,
          "specialAction": null
        },
        "comment": "2 drones back to 1st gas"
      },
      {
        "supply": "51",
        "time": "4:13",
        "action": "Zergling x6",
        "interpretedAction": {
          "unitType": 105,
          "upgradeType": null,
          "count": 6,
          "isUpgrade": false,
          "isChronoBoosted": false,
          "specialAction": null
        },
        "comment": ""
      },
      {
        "supply": "65",
        "time": "4:40",
        "action": "Hydralisk Den",
        "interpretedAction": {
          "unitType": 91,
          "upgradeType": null,
          "count": 1,
          "isUpgrade": false,
          "isChronoBoosted": false,
          "specialAction": null
        },
        "comment": ""
      },
      {
        "supply": "65",
        "time": "4:41",
        "action": "Extractor x3",
        "interpretedAction": {
          "unitType": 88,
          "upgradeType": null,
          "count": 3,
          "isUpgrade": false,
          "isChronoBoosted": false,
          "specialAction": null
        },
        "comment": ""
      },
      {
        "supply": "74",
        "time": "5:23",
        "action": "Hydralisk x4",
        "interpretedAction": {
          "unitType": 107,
          "upgradeType": null,
          "count": 4,
          "isUpgrade": false,
          "isChronoBoosted": false,
          "specialAction": null
        },
        "comment": ""
      },
      {
        "supply": "74",
        "time": "5:25",
        "action": "Hatchery",
        "interpretedAction": {
          "unitType": 86,
          "upgradeType": null,
          "count": 1,
          "isUpgrade": false,
          "isChronoBoosted": false,
          "specialAction": null
        },
        "comment": ""
      },
      {
        "supply": "80",
        "time": "5:33",
        "action": "Hydralisk x5",
        "interpretedAction": {
          "unitType": 107,
          "upgradeType": null,
          "count": 5,
          "isUpgrade": false,
          "isChronoBoosted": false,
          "specialAction": null
        },
        "comment": ""
      },
      {
        "supply": "88",
        "time": "5:38",
        "action": "Evolution Chamber",
        "interpretedAction": {
          "unitType": 90,
          "upgradeType": null,
          "count": 1,
          "isUpgrade": false,
          "isChronoBoosted": false,
          "specialAction": null
        },
        "comment": ""
      },
      {
        "supply": "90",
        "time": "5:44",
        "action": "Baneling Nest",
        "interpretedAction": {
          "unitType": 96,
          "upgradeType": null,
          "count": 1,
          "isUpgrade": false,
          "isChronoBoosted": false,
          "specialAction": null
        },
        "comment": ""
      },
      {
        "supply": "90",
        "time": "5:45",
        "action": "Hydralisk",
        "interpretedAction": {
          "unitType": 107,
          "upgradeType": null,
          "count": 1,
          "isUpgrade": false,
          "isChronoBoosted": false,
          "specialAction": null
        },
        "comment": ""
      },
      {
        "supply": "93",
        "time": "5:51",
        "action": "Zergling x12",
        "interpretedAction": {
          "unitType": 105,
          "upgradeType": null,
          "count": 12,
          "isUpgrade": false,
          "isChronoBoosted": false,
          "specialAction": null
        },
        "comment": ""
      },
      {
        "supply": "103",
        "time": "5:57",
        "action": "Spore Crawler x3",
        "interpretedAction": {
          "unitType": 99,
          "upgradeType": null,
          "count": 3,
          "isUpgrade": false,
          "isChronoBoosted": false,
          "specialAction": null
        },
        "comment": ""
      },
      {
        "supply": "100",
        "time": "6:06",
        "action": "Spore Crawler",
        "interpretedAction": {
          "unitType": 99,
          "upgradeType": null,
          "count": 1,
          "isUpgrade": false,
          "isChronoBoosted": false,
          "specialAction": null
        },
        "comment": ""
      },
      {
        "supply": "105",
        "time": "6:22",
        "action": "Grooved Spines",
        "interpretedAction": {
          "unitType": null,
          "upgradeType": null,
          "count": 1,
          "isUpgrade": false,
          "isChronoBoosted": false,
          "specialAction": null
        },
        "comment": ""
      },
      {
        "supply": "126",
        "time": "7:21",
        "action": "Baneling x10",
        "interpretedAction": {
          "unitType": 9,
          "upgradeType": null,
          "count": 10,
          "isUpgrade": false,
          "isChronoBoosted": false,
          "specialAction": null
        },
        "comment": ""
      }
    ],
    "raceMatchup": "ZvX",
    "url": "https://lotv.spawningtool.com/build/180325/"
  },
  {
    "title": "Vortix 66 drones",
    "steps": [
      {
        "supply": "13",
        "time": "0:15",
        "action": "Overlord",
        "interpretedAction": {
          "unitType": 106,
          "upgradeType": null,
          "count": 1,
          "isUpgrade": false,
          "isChronoBoosted": false,
          "specialAction": null
        },
        "comment": ""
      },
      {
        "supply": "16",
        "time": "0:48",
        "action": "Hatchery",
        "interpretedAction": {
          "unitType": 86,
          "upgradeType": null,
          "count": 1,
          "isUpgrade": false,
          "isChronoBoosted": false,
          "specialAction": null
        },
        "comment": ""
      },
      {
        "supply": "16",
        "time": "1:10",
        "action": "Extractor",
        "interpretedAction": {
          "unitType": 88,
          "upgradeType": null,
          "count": 1,
          "isUpgrade": false,
          "isChronoBoosted": false,
          "specialAction": null
        },
        "comment": ""
      },
      {
        "supply": "16",
        "time": "1:12",
        "action": "Spawning Pool",
        "interpretedAction": {
          "unitType": 89,
          "upgradeType": null,
          "count": 1,
          "isUpgrade": false,
          "isChronoBoosted": false,
          "specialAction": null
        },
        "comment": ""
      },
      {
        "supply": "19",
        "time": "1:30",
        "action": "Drone x3",
        "interpretedAction": {
          "unitType": 104,
          "upgradeType": null,
          "count": 3,
          "isUpgrade": false,
          "isChronoBoosted": false,
          "specialAction": null
        },
        "comment": "To gas"
      },
      {
        "supply": "20",
        "time": "1:49",
        "action": "Overlord",
        "interpretedAction": {
          "unitType": 106,
          "upgradeType": null,
          "count": 1,
          "isUpgrade": false,
          "isChronoBoosted": false,
          "specialAction": null
        },
        "comment": ""
      },
      {
        "supply": "25",
        "time": "2:04",
        "action": "Zergling x4, Queen x2",
        "interpretedAction": {
          "unitType": 105,
          "upgradeType": null,
          "count": 4,
          "isUpgrade": false,
          "isChronoBoosted": false,
          "specialAction": null
        },
        "comment": ""
      },
      {
        "supply": "25",
        "time": "2:04",
        "action": "Zergling x4, Queen x2",
        "interpretedAction": {
          "unitType": 126,
          "upgradeType": null,
          "count": 4,
          "isUpgrade": false,
          "isChronoBoosted": false,
          "specialAction": null
        },
        "comment": ""
      },
      {
        "supply": "28",
        "time": "2:19",
        "action": "Metabolic Boost",
        "interpretedAction": {
          "unitType": null,
          "upgradeType": null,
          "count": 1,
          "isUpgrade": false,
          "isChronoBoosted": false,
          "specialAction": null
        },
        "comment": ""
      },
      {
        "supply": "28",
        "time": "2:20",
        "action": "Drone x3",
        "interpretedAction": {
          "unitType": 104,
          "upgradeType": null,
          "count": 3,
          "isUpgrade": false,
          "isChronoBoosted": false,
          "specialAction": null
        },
        "comment": "Out of gas"
      },
      {
        "supply": "30",
        "time": "2:36",
        "action": "Hatchery",
        "interpretedAction": {
          "unitType": 86,
          "upgradeType": null,
          "count": 1,
          "isUpgrade": false,
          "isChronoBoosted": false,
          "specialAction": null
        },
        "comment": ""
      },
      {
        "supply": "31",
        "time": "2:45",
        "action": "Queen",
        "interpretedAction": {
          "unitType": 126,
          "upgradeType": null,
          "count": 1,
          "isUpgrade": false,
          "isChronoBoosted": false,
          "specialAction": null
        },
        "comment": ""
      },
      {
        "supply": "33",
        "time": "2:52",
        "action": "Overlord",
        "interpretedAction": {
          "unitType": 106,
          "upgradeType": null,
          "count": 1,
          "isUpgrade": false,
          "isChronoBoosted": false,
          "specialAction": null
        },
        "comment": ""
      },
      {
        "supply": "43",
        "time": "3:25",
        "action": "Queen x3",
        "interpretedAction": {
          "unitType": 126,
          "upgradeType": null,
          "count": 3,
          "isUpgrade": false,
          "isChronoBoosted": false,
          "specialAction": null
        },
        "comment": ""
      },
      {
        "supply": "66",
        "time": "4:15",
        "action": "Extractor",
        "interpretedAction": {
          "unitType": 88,
          "upgradeType": null,
          "count": 1,
          "isUpgrade": false,
          "isChronoBoosted": false,
          "specialAction": null
        },
        "comment": ""
      },
      {
        "supply": "67",
        "time": "4:25",
        "action": "Lair",
        "interpretedAction": {
          "unitType": 100,
          "upgradeType": null,
          "count": 1,
          "isUpgrade": false,
          "isChronoBoosted": false,
          "specialAction": null
        },
        "comment": ""
      },
      {
        "supply": "67",
        "time": "4:30",
        "action": "Hatchery",
        "interpretedAction": {
          "unitType": 86,
          "upgradeType": null,
          "count": 1,
          "isUpgrade": false,
          "isChronoBoosted": false,
          "specialAction": null
        },
        "comment": ""
      },
      {
        "supply": "76",
        "time": "4:55",
        "action": "Roach Warren",
        "interpretedAction": {
          "unitType": 97,
          "upgradeType": null,
          "count": 1,
          "isUpgrade": false,
          "isChronoBoosted": false,
          "specialAction": null
        },
        "comment": ""
      }
    ],
    "raceMatchup": "ZvX",
    "url": "https://lotv.spawningtool.com/build/179921/"
  }
]